{"AB125AA": ["57.125990", "-2.106797", "S12000033", "Aberdeen City", "S13002847", "Kincorth/Nigg/Cove"], "AB125AB": ["57.125768", "-2.103857", "S12000033", "Aberdeen City", "S13002847", "Kincorth/Nigg/Cove"], "AB125AD": ["57.125222", "-2.101278", "S12000033", "Aberdeen City", "S13002847", "Kincorth/Nigg/Cove"], "AB125AE": ["57.125050", "-2.103177", "S12000033", "Aberdeen City", "S13002847", "Kincorth/Nigg/Cove"], "AB125AF": ["57.084219", "-2.232509", "S12000034", "Aberdeenshire", "S13002864", "North Kincardine"], "AB125AH": ["57.125544", "-2.103988", "S12000033", "Aberdeen City", "S13002847", "Kincorth/Nigg/Cove"], "AB125AJ": ["57.125003", "-2.105539", "S12000033", "Aberdeen City", "S13002847", "Kincorth/Nigg/Cove"], "AB125AL": ["57.125371", "-2.106548", "S12000033", "Aberdeen City", "S13002847", "Kincorth/Nigg/Cove"], "AB125AN": ["57.125721", "-2.106450", "S12000033", "Aberdeen City", "S13002847", "Kincorth/Nigg/Cove"], "AB125AP": ["57.124797", "-2.104894", "S12000033", "Aberdeen City", "S13002847", "Kincorth/Nigg/Cove"], "AB125AQ": ["57.124754", "-2.102483", "S12000033", "Aberdeen City", "S13002847", "Kincorth/Nigg/Cove"], "AB125AR": ["57.124389", "-2.101681", "S12000033", "Aberdeen City", "S13002847", "Kincorth/Nigg/Cove"], "AB125AS": ["57.123660", "-2.100432", "S12000033", "Aberdeen City", "S13002847", "Kincorth/Nigg/Cove"], "AB125AT": ["57.123033", "-2.097936", "S12000033", "Aberdeen City", "S13002847", "Kincorth/Nigg/Cove"], "AB125AU": ["57.122017", "-2.099123", "S12000033", "Aberdeen City", "S13002847", "Kincorth/Nigg/Cove"], "AB125AX": ["57.121882", "-2.102235", "S12000033", "Aberdeen City", "S13002847", "Kincorth/Nigg/Cove"], "AB125AY": ["57.122366", "-2.100610", "S12000033", "Aberdeen City", "S13002847", "Kincorth/Nigg/Cove"], "AB125BA": ["57.123013", "-2.100959", "S12000033", "Aberdeen City", "S13002847", "Kincorth/Nigg/Cove"], "AB125BB": ["57.123346", "-2.100332", "S12000033", "Aberdeen City", "S13002847", "Kincorth/Nigg/Cove"], "AB125BD": ["57.121741", "-2.096793", "S12000033", "Aberdeen City", "S13002847", "Kincorth/Nigg/Cove"], "AB125BE": ["57.120107", "-2.095105", "S12000033", "Aberdeen City", "S13002847", "Kincorth/Nigg/Cove"], "AB125BH": ["57.119344", "-2.093864", "S12000033", "Aberdeen City", "S13002847", "Kincorth/Nigg/Cove"], "AB125BJ": ["57.118743", "-2.092954", "S12000033", "Aberdeen City", "S13002847", "Kincorth/Nigg/Cove"], "AB125BL": ["57.121155", "-2.099517", "S12000033", "Aberdeen City", "S13002847", "Kincorth/Nigg/Cove"], "AB125BN": ["57.121021", "-2.098525", "S12000033", "Aberdeen City", "S13002847", "Kincorth/Nigg/Cove"], "AB125BP": ["57.121836", "-2.101170", "S12000033", "Aberdeen City", "S13002847", "Kincorth/Nigg/Cove"], "AB125BQ": ["57.121243", "-2.101482", "S12000033", "Aberdeen City", "S13002847", "Kincorth/Nigg/Cove"], "AB125BR": ["57.121709", "-2.102359", "S12000033", "Aberdeen City", "S13002847", "Kincorth/Nigg/Cove"], "AB125BS": ["57.120416", "-2.101596", "S12000033", "Aberdeen City", "S13002847", "Kincorth/Nigg/Cove"], "AB125BT": ["57.120696", "-2.102711", "S12000033", "Aberdeen City", "S13002847", "Kincorth/Nigg/Cove"], "AB125BU": ["57.119681", "-2.102989", "S12000033", "Aberdeen City", "S13002847", "Kincorth/Nigg/Cove"], "AB125BX": ["57.119454", "-2.102567", "S12000033", "Aberdeen City", "S13002847", "Kincorth/Nigg/Cove"], "AB125BY": ["57.119511", "-2.102064", "S12000033", "Aberdeen City", "S13002847", "Kincorth/Nigg/Cove"], "AB125BZ": ["57.082699", "-2.238588", "S12000034", "Aberdeenshire", "S13002864", "North Kincardine"], "AB125DA": ["57.120653", "-2.097286", "S12000033", "Aberdeen City", "S13002847", "Kincorth/Nigg/Cove"], "AB125DB": ["57.120168", "-2.097136", "S12000033", "Aberdeen City", "S13002847", "Kincorth/Nigg/Cove"], "AB125DD": ["57.119493", "-2.099199", "S12000033", "Aberdeen City", "S13002847", "Kincorth/Nigg/Cove"], "AB125DE": ["57.119339", "-2.100205", "S12000033", "Aberdeen City", "S13002847", "Kincorth/Nigg/Cove"], "AB125DF": ["57.121054", "-2.101746", "S12000033", "Aberdeen City", "S13002847", "Kincorth/Nigg/Cove"], "AB125DH": ["57.118988", "-2.102071", "S12000033", "Aberdeen City", "S13002847", "Kincorth/Nigg/Cove"], "AB125DJ": ["57.117975", "-2.099525", "S12000033", "Aberdeen City", "S13002847", "Kincorth/Nigg/Cove"], "AB125DL": ["57.118647", "-2.101128", "S12000033", "Aberdeen City", "S13002847", "Kincorth/Nigg/Cove"], "AB125DN": ["57.118405", "-2.099840", "S12000033", "Aberdeen City", "S13002847", "Kincorth/Nigg/Cove"], "AB125DP": ["57.117779", "-2.096453", "S12000033", "Aberdeen City", "S13002847", "Kincorth/Nigg/Cove"], "AB125DQ": ["57.118311", "-2.094522", "S12000033", "Aberdeen City", "S13002847", "Kincorth/Nigg/Cove"], "AB125DR": ["57.118832", "-2.094061", "S12000033", "Aberdeen City", "S13002847", "Kincorth/Nigg/Cove"], "AB125DS": ["57.118966", "-2.094904", "S12000033", "Aberdeen City", "S13002847", "Kincorth/Nigg/Cove"], "AB125DT": ["57.118957", "-2.095498", "S12000033", "Aberdeen City", "S13002847", "Kincorth/Nigg/Cove"], "AB125DX": ["57.118561", "-2.096769", "S12000033", "Aberdeen City", "S13002847", "Kincorth/Nigg/Cove"], "AB125EA": ["57.118406", "-2.098634", "S12000033", "Aberdeen City", "S13002847", "Kincorth/Nigg/Cove"], "AB125EB": ["57.118902", "-2.096753", "S12000033", "Aberdeen City", "S13002847", "Kincorth/Nigg/Cove"], "AB125ED": ["57.119009", "-2.097761", "S12000033", "Aberdeen City", "S13002847", "Kincorth/Nigg/Cove"], "AB125EJ": ["57.119425", "-2.094558", "S12000033", "Aberdeen City", "S13002847", "Kincorth/Nigg/Cove"], "AB125EL": ["57.119899", "-2.096904", "S12000033", "Aberdeen City", "S13002847", "Kincorth/Nigg/Cove"], "AB125EN": ["57.119278", "-2.097877", "S12000033", "Aberdeen City", "S13002847", "Kincorth/Nigg/Cove"], "AB125EP": ["57.119133", "-2.099990", "S12000033", "Aberdeen City", "S13002847", "Kincorth/Nigg/Cove"], "AB125EQ": ["57.118376", "-2.103093", "S12000033", "Aberdeen City", "S13002847", "Kincorth/Nigg/Cove"], "AB125ER": ["57.117826", "-2.104858", "S12000033", "Aberdeen City", "S13002847", "Kincorth/Nigg/Cove"], "AB125ES": ["57.117844", "-2.105403", "S12000033", "Aberdeen City", "S13002847", "Kincorth/Nigg/Cove"], "AB125ET": ["57.116990", "-2.106045", "S12000033", "Aberdeen City", "S13002847", "Kincorth/Nigg/Cove"], "AB125EX": ["57.117403", "-2.106541", "S12000033", "Aberdeen City", "S13002847", "Kincorth/Nigg/Cove"], "AB125FA": ["57.062025", "-2.237274", "S12000034", "Aberdeenshire", "S13002864", "North Kincardine"], "AB125FB": ["57.070209", "-2.244857", "S12000034", "Aberdeenshire", "S13002864", "North Kincardine"], "AB125FD": ["57.097810", "-2.228006", "S12000034", "Aberdeenshire", "S13002864", "North Kincardine"], "AB125FE": ["57.083669", "-2.256857", "S12000034", "Aberdeenshire", "S13002864", "North Kincardine"], "AB125FF": ["57.084714", "-2.255445", "S12000034", "Aberdeenshire", "S13002864", "North Kincardine"], "AB125FR": ["57.091357", "-2.224831", "S12000034", "Aberdeenshire", "S13002864", "North Kincardine"], "AB125FS": ["57.083838", "-2.234437", "S12000034", "Aberdeenshire", "S13002864", "North Kincardine"], "AB125FT": ["57.089012", "-2.239486", "S12000034", "Aberdeenshire", "S13002864", "North Kincardine"], "AB125FX": ["57.095625", "-2.248210", "S12000034", "Aberdeenshire", "S13002864", "North Kincardine"], "AB125GA": ["57.091298", "-2.257065", "S12000034", "Aberdeenshire", "S13002864", "North Kincardine"], "AB125GB": ["57.084869", "-2.258746", "S12000034", "Aberdeenshire", "S13002864", "North Kincardine"], "AB125GD": ["57.074716", "-2.280547", "S12000034", "Aberdeenshire", "S13002864", "North Kincardine"], "AB125GE": ["57.090764", "-2.257434", "S12000034", "Aberdeenshire", "S13002864", "North Kincardine"], "AB125GF": ["57.111340", "-2.093992", "S12000033", "Aberdeen City", "S13002847", "Kincorth/Nigg/Cove"], "AB125GH": ["57.071783", "-2.252965", "S12000034", "Aberdeenshire", "S13002864", "North Kincardine"], "AB125GJ": ["57.081421", "-2.262319", "S12000034", "Aberdeenshire", "S13002864", "North Kincardine"], "AB125GL": ["57.081938", "-2.246567", "S12000034", "Aberdeenshire", "S13002864", "North Kincardine"], "AB125GN": ["57.071507", "-2.251627", "S12000034", "Aberdeenshire", "S13002864", "North Kincardine"], "AB125GP": ["57.063794", "-2.268912", "S12000034", "Aberdeenshire", "S13002864", "North Kincardine"], "AB125GQ": ["57.065919", "-2.289517", "S12000034", "Aberdeenshire", "S13002864", "North Kincardine"], "AB125GR": ["57.058313", "-2.272180", "S12000034", "Aberdeenshire", "S13002864", "North Kincardine"], "AB125GS": ["57.051734", "-2.269510", "S12000034", "Aberdeenshire", "S13002864", "North Kincardine"], "AB125GT": ["57.058830", "-2.249784", "S12000034", "Aberdeenshire", "S13002864", "North Kincardine"], "AB125GW": ["57.067648", "-2.260266", "S12000034", "Aberdeenshire", "S13002864", "North Kincardine"], "AB125GX": ["57.069302", "-2.235582", "S12000034", "Aberdeenshire", "S13002864", "North Kincardine"], "AB125GY": ["57.082280", "-2.236671", "S12000034", "Aberdeenshire", "S13002864", "North Kincardine"], "AB125GZ": ["57.083818", "-2.236021", "S12000034", "Aberdeenshire", "S13002864", "North Kincardine"], "AB125HA": ["57.117124", "-2.107234", "S12000033", "Aberdeen City", "S13002847", "Kincorth/Nigg/Cove"], "AB125HB": ["57.116000", "-2.108684", "S12000033", "Aberdeen City", "S13002847", "Kincorth/Nigg/Cove"], "AB125HD": ["57.116557", "-2.108223", "S12000033", "Aberdeen City", "S13002847", "Kincorth/Nigg/Cove"], "AB125HJ": ["57.116322", "-2.110105", "S12000033", "Aberdeen City", "S13002847", "Kincorth/Nigg/Cove"], "AB125HL": ["57.116670", "-2.112137", "S12000033", "Aberdeen City", "S13002847", "Kincorth/Nigg/Cove"], "AB125HN": ["57.116480", "-2.113804", "S12000033", "Aberdeen City", "S13002847", "Kincorth/Nigg/Cove"], "AB125HP": ["57.116373", "-2.112648", "S12000033", "Aberdeen City", "S13002847", "Kincorth/Nigg/Cove"], "AB125HQ": ["57.116555", "-2.110898", "S12000033", "Aberdeen City", "S13002847", "Kincorth/Nigg/Cove"], "AB125HR": ["57.117255", "-2.111065", "S12000033", "Aberdeen City", "S13002847", "Kincorth/Nigg/Cove"], "AB125HS": ["57.117802", "-2.112421", "S12000033", "Aberdeen City", "S13002847", "Kincorth/Nigg/Cove"], "AB125HT": ["57.118003", "-2.111456", "S12000033", "Aberdeen City", "S13002847", "Kincorth/Nigg/Cove"], "AB125HX": ["57.117498", "-2.110587", "S12000033", "Aberdeen City", "S13002847", "Kincorth/Nigg/Cove"], "AB125JA": ["57.116771", "-2.109644", "S12000033", "Aberdeen City", "S13002847", "Kincorth/Nigg/Cove"], "AB125JB": ["57.117742", "-2.109349", "S12000033", "Aberdeen City", "S13002847", "Kincorth/Nigg/Cove"], "AB125JD": ["57.117941", "-2.107600", "S12000033", "Aberdeen City", "S13002847", "Kincorth/Nigg/Cove"], "AB125JE": ["57.116958", "-2.089466", "S12000033", "Aberdeen City", "S13002847", "Kincorth/Nigg/Cove"], "AB125JF": ["57.116319", "-2.091446", "S12000033", "Aberdeen City", "S13002847", "Kincorth/Nigg/Cove"], "AB125JG": ["57.116616", "-2.089911", "S12000033", "Aberdeen City", "S13002847", "Kincorth/Nigg/Cove"], "AB125JJ": ["57.117978", "-2.106047", "S12000033", "Aberdeen City", "S13002847", "Kincorth/Nigg/Cove"], "AB125JL": ["57.116853", "-2.108356", "S12000033", "Aberdeen City", "S13002847", "Kincorth/Nigg/Cove"], "AB125JN": ["57.116313", "-2.109411", "S12000033", "Aberdeen City", "S13002847", "Kincorth/Nigg/Cove"], "AB125JP": ["57.115729", "-2.110334", "S12000033", "Aberdeen City", "S13002847", "Kincorth/Nigg/Cove"], "AB125JQ": ["57.115728", "-2.111110", "S12000033", "Aberdeen City", "S13002847", "Kincorth/Nigg/Cove"], "AB125JR": ["57.115385", "-2.112579", "S12000033", "Aberdeen City", "S13002847", "Kincorth/Nigg/Cove"], "AB125JS": ["57.115098", "-2.112528", "S12000033", "Aberdeen City", "S13002847", "Kincorth/Nigg/Cove"], "AB125JT": ["57.115879", "-2.113224", "S12000033", "Aberdeen City", "S13002847", "Kincorth/Nigg/Cove"], "AB125JU": ["57.115108", "-2.110894", "S12000033", "Aberdeen City", "S13002847", "Kincorth/Nigg/Cove"], "AB125JW": ["57.124305", "-2.102465", "S12000033", "Aberdeen City", "S13002847", "Kincorth/Nigg/Cove"], "AB125JX": ["57.115465", "-2.114362", "S12000033", "Aberdeen City", "S13002847", "Kincorth/Nigg/Cove"], "AB125JY": ["57.115266", "-2.115204", "S12000033", "Aberdeen City", "S13002847", "Kincorth/Nigg/Cove"], "AB125LA": ["57.114926", "-2.113486", "S12000033", "Aberdeen City", "S13002847", "Kincorth/Nigg/Cove"], "AB125LB": ["57.114577", "-2.115094", "S12000033", "Aberdeen City", "S13002847", "Kincorth/Nigg/Cove"], "AB125LD": ["57.114376", "-2.116225", "S12000033", "Aberdeen City", "S13002847", "Kincorth/Nigg/Cove"], "AB125LE": ["57.114724", "-2.111396", "S12000033", "Aberdeen City", "S13002847", "Kincorth/Nigg/Cove"], "AB125LF": ["57.098872", "-2.195135", "S12000034", "Aberdeenshire", "S13002864", "North Kincardine"], "AB125LJ": ["57.114153", "-2.114656", "S12000033", "Aberdeen City", "S13002847", "Kincorth/Nigg/Cove"], "AB125LL": ["57.114486", "-2.113369", "S12000033", "Aberdeen City", "S13002847", "Kincorth/Nigg/Cove"], "AB125LN": ["57.113588", "-2.113482", "S12000033", "Aberdeen City", "S13002847", "Kincorth/Nigg/Cove"], "AB125LP": ["57.114820", "-2.112049", "S12000033", "Aberdeen City", "S13002847", "Kincorth/Nigg/Cove"], "AB125LQ": ["57.113121", "-2.113348", "S12000033", "Aberdeen City", "S13002847", "Kincorth/Nigg/Cove"], "AB125LR": ["57.113372", "-2.114372", "S12000033", "Aberdeen City", "S13002847", "Kincorth/Nigg/Cove"], "AB125LS": ["57.112957", "-2.115296", "S12000033", "Aberdeen City", "S13002847", "Kincorth/Nigg/Cove"], "AB125LT": ["57.112706", "-2.115378", "S12000033", "Aberdeen City", "S13002847", "Kincorth/Nigg/Cove"], "AB125LX": ["57.112563", "-2.114139", "S12000033", "Aberdeen City", "S13002847", "Kincorth/Nigg/Cove"], "AB125NA": ["57.120827", "-2.104090", "S12000033", "Aberdeen City", "S13002847", "Kincorth/Nigg/Cove"], "AB125NB": ["57.119929", "-2.104203", "S12000033", "Aberdeen City", "S13002847", "Kincorth/Nigg/Cove"], "AB125ND": ["57.119192", "-2.104565", "S12000033", "Aberdeen City", "S13002847", "Kincorth/Nigg/Cove"], "AB125NE": ["57.111340", "-2.093992", "S12000033", "Aberdeen City", "S13002847", "Kincorth/Nigg/Cove"], "AB125NJ": ["57.119245", "-2.105704", "S12000033", "Aberdeen City", "S13002847", "Kincorth/Nigg/Cove"], "AB125NL": ["57.119541", "-2.105920", "S12000033", "Aberdeen City", "S13002847", "Kincorth/Nigg/Cove"], "AB125NN": ["57.120692", "-2.104718", "S12000033", "Aberdeen City", "S13002847", "Kincorth/Nigg/Cove"], "AB125NP": ["57.121745", "-2.105142", "S12000033", "Aberdeen City", "S13002847", "Kincorth/Nigg/Cove"], "AB125NQ": ["57.122218", "-2.106225", "S12000033", "Aberdeen City", "S13002847", "Kincorth/Nigg/Cove"], "AB125NR": ["57.122568", "-2.106820", "S12000033", "Aberdeen City", "S13002847", "Kincorth/Nigg/Cove"], "AB125NS": ["57.121903", "-2.106488", "S12000033", "Aberdeen City", "S13002847", "Kincorth/Nigg/Cove"], "AB125NT": ["57.121331", "-2.106544", "S12000033", "Aberdeen City", "S13002847", "Kincorth/Nigg/Cove"], "AB125NX": ["57.121264", "-2.108468", "S12000033", "Aberdeen City", "S13002847", "Kincorth/Nigg/Cove"], "AB125PA": ["57.121667", "-2.109245", "S12000033", "Aberdeen City", "S13002847", "Kincorth/Nigg/Cove"], "AB125PB": ["57.120506", "-2.111703", "S12000033", "Aberdeen City", "S13002847", "Kincorth/Nigg/Cove"], "AB125PD": ["57.119808", "-2.112435", "S12000033", "Aberdeen City", "S13002847", "Kincorth/Nigg/Cove"], "AB125PE": ["57.125349", "-2.110644", "S12000033", "Aberdeen City", "S13002847", "Kincorth/Nigg/Cove"], "AB125PF": ["57.121244", "-2.110301", "S12000033", "Aberdeen City", "S13002847", "Kincorth/Nigg/Cove"], "AB125PJ": ["57.119159", "-2.112161", "S12000033", "Aberdeen City", "S13002847", "Kincorth/Nigg/Cove"], "AB125PL": ["57.118592", "-2.112374", "S12000033", "Aberdeen City", "S13002847", "Kincorth/Nigg/Cove"], "AB125PN": ["57.118278", "-2.112274", "S12000033", "Aberdeen City", "S13002847", "Kincorth/Nigg/Cove"], "AB125PP": ["57.118360", "-2.110606", "S12000033", "Aberdeen City", "S13002847", "Kincorth/Nigg/Cove"], "AB125PQ": ["57.118446", "-2.108534", "S12000033", "Aberdeen City", "S13002847", "Kincorth/Nigg/Cove"], "AB125PR": ["57.118326", "-2.108905", "S12000033", "Aberdeen City", "S13002847", "Kincorth/Nigg/Cove"], "AB125PS": ["57.118534", "-2.106842", "S12000033", "Aberdeen City", "S13002847", "Kincorth/Nigg/Cove"], "AB125PT": ["57.118607", "-2.105537", "S12000033", "Aberdeen City", "S13002847", "Kincorth/Nigg/Cove"], "AB125PX": ["57.118681", "-2.103655", "S12000033", "Aberdeen City", "S13002847", "Kincorth/Nigg/Cove"], "AB125QA": ["57.119058", "-2.103838", "S12000033", "Aberdeen City", "S13002847", "Kincorth/Nigg/Cove"], "AB125QB": ["57.119417", "-2.103641", "S12000033", "Aberdeen City", "S13002847", "Kincorth/Nigg/Cove"], "AB125QD": ["57.125277", "-2.110693", "S12000033", "Aberdeen City", "S13002847", "Kincorth/Nigg/Cove"], "AB125QJ": ["57.124801", "-2.110857", "S12000033", "Aberdeen City", "S13002847", "Kincorth/Nigg/Cove"], "AB125QL": ["57.124036", "-2.113134", "S12000033", "Aberdeen City", "S13002847", "Kincorth/Nigg/Cove"], "AB125QN": ["57.123929", "-2.112225", "S12000033", "Aberdeen City", "S13002847", "Kincorth/Nigg/Cove"], "AB125QP": ["57.122876", "-2.114105", "S12000033", "Aberdeen City", "S13002847", "Kincorth/Nigg/Cove"], "AB125QQ": ["57.123787", "-2.109945", "S12000033", "Aberdeen City", "S13002847", "Kincorth/Nigg/Cove"], "AB125QR": ["57.123978", "-2.107320", "S12000033", "Aberdeen City", "S13002847", "Kincorth/Nigg/Cove"], "AB125QS": ["57.123268", "-2.107516", "S12000033", "Aberdeen City", "S13002847", "Kincorth/Nigg/Cove"], "AB125QT": ["57.122582", "-2.111676", "S12000033", "Aberdeen City", "S13002847", "Kincorth/Nigg/Cove"], "AB125QU": ["57.124551", "-2.109089", "S12000033", "Aberdeen City", "S13002847", "Kincorth/Nigg/Cove"], "AB125QX": ["57.122828", "-2.106821", "S12000033", "Aberdeen City", "S13002847", "Kincorth/Nigg/Cove"], "AB125RA": ["57.120730", "-2.112909", "S12000033", "Aberdeen City", "S13002847", "Kincorth/Nigg/Cove"], "AB125RB": ["57.119185", "-2.113020", "S12000033", "Aberdeen City", "S13002847", "Kincorth/Nigg/Cove"], "AB125RD": ["57.119831", "-2.113814", "S12000033", "Aberdeen City", "S13002847", "Kincorth/Nigg/Cove"], "AB125RE": ["57.112320", "-2.114931", "S12000033", "Aberdeen City", "S13002847", "Kincorth/Nigg/Cove"], "AB125RF": ["57.112130", "-2.116267", "S12000033", "Aberdeen City", "S13002847", "Kincorth/Nigg/Cove"], "AB125RG": ["57.110056", "-2.114907", "S12000033", "Aberdeen City", "S13002847", "Kincorth/Nigg/Cove"], "AB125RH": ["57.111197", "-2.114679", "S12000033", "Aberdeen City", "S13002847", "Kincorth/Nigg/Cove"], "AB125RJ": ["57.120091", "-2.114311", "S12000033", "Aberdeen City", "S13002847", "Kincorth/Nigg/Cove"], "AB125RL": ["57.120665", "-2.114940", "S12000033", "Aberdeen City", "S13002847", "Kincorth/Nigg/Cove"], "AB125RN": ["57.122572", "-2.112469", "S12000033", "Aberdeen City", "S13002847", "Kincorth/Nigg/Cove"], "AB125RP": ["57.122445", "-2.113855", "S12000033", "Aberdeen City", "S13002847", "Kincorth/Nigg/Cove"], "AB125RQ": ["57.120539", "-2.115864", "S12000033", "Aberdeen City", "S13002847", "Kincorth/Nigg/Cove"], "AB125RR": ["57.118869", "-2.114555", "S12000033", "Aberdeen City", "S13002847", "Kincorth/Nigg/Cove"], "AB125RT": ["57.112636", "-2.116079", "S12000033", "Aberdeen City", "S13002847", "Kincorth/Nigg/Cove"], "AB125RU": ["57.111484", "-2.115159", "S12000033", "Aberdeen City", "S13002847", "Kincorth/Nigg/Cove"], "AB125RW": ["57.111304", "-2.115670", "S12000033", "Aberdeen City", "S13002847", "Kincorth/Nigg/Cove"], "AB125RX": ["57.113684", "-2.116074", "S12000033", "Aberdeen City", "S13002847", "Kincorth/Nigg/Cove"], "AB125RY": ["57.111672", "-2.116117", "S12000033", "Aberdeen City", "S13002847", "Kincorth/Nigg/Cove"], "AB125RZ": ["57.110936", "-2.115620", "S12000033", "Aberdeen City", "S13002847", "Kincorth/Nigg/Cove"], "AB125SA": ["57.113953", "-2.116785", "S12000033", "Aberdeen City", "S13002847", "Kincorth/Nigg/Cove"], "AB125SB": ["57.115392", "-2.115270", "S12000033", "Aberdeen City", "S13002847", "Kincorth/Nigg/Cove"], "AB125SD": ["57.115760", "-2.115899", "S12000033", "Aberdeen City", "S13002847", "Kincorth/Nigg/Cove"], "AB125SE": ["57.109354", "-2.116523", "S12000033", "Aberdeen City", "S13002847", "Kincorth/Nigg/Cove"], "AB125SF": ["57.110091", "-2.116096", "S12000033", "Aberdeen City", "S13002847", "Kincorth/Nigg/Cove"], "AB125SJ": ["57.116003", "-2.114430", "S12000033", "Aberdeen City", "S13002847", "Kincorth/Nigg/Cove"], "AB125SL": ["57.116398", "-2.114729", "S12000033", "Aberdeen City", "S13002847", "Kincorth/Nigg/Cove"], "AB125SN": ["57.117136", "-2.113624", "S12000033", "Aberdeen City", "S13002847", "Kincorth/Nigg/Cove"], "AB125SP": ["57.118001", "-2.113536", "S12000033", "Aberdeen City", "S13002847", "Kincorth/Nigg/Cove"], "AB125SQ": ["57.117764", "-2.114221", "S12000033", "Aberdeen City", "S13002847", "Kincorth/Nigg/Cove"], "AB125SR": ["57.117802", "-2.115055", "S12000033", "Aberdeen City", "S13002847", "Kincorth/Nigg/Cove"], "AB125SS": ["57.117781", "-2.115658", "S12000033", "Aberdeen City", "S13002847", "Kincorth/Nigg/Cove"], "AB125ST": ["57.117287", "-2.115243", "S12000033", "Aberdeen City", "S13002847", "Kincorth/Nigg/Cove"], "AB125SU": ["57.116577", "-2.115902", "S12000033", "Aberdeen City", "S13002847", "Kincorth/Nigg/Cove"], "AB125SX": ["57.117600", "-2.116615", "S12000033", "Aberdeen City", "S13002847", "Kincorth/Nigg/Cove"], "AB125SZ": ["57.115804", "-2.116378", "S12000033", "Aberdeen City", "S13002847", "Kincorth/Nigg/Cove"], "AB125TA": ["57.118336", "-2.117344", "S12000033", "Aberdeen City", "S13002847", "Kincorth/Nigg/Cove"], "AB125TB": ["57.117995", "-2.116946", "S12000033", "Aberdeen City", "S13002847", "Kincorth/Nigg/Cove"], "AB125TD": ["57.117168", "-2.117802", "S12000033", "Aberdeen City", "S13002847", "Kincorth/Nigg/Cove"], "AB125TJ": ["57.116848", "-2.117380", "S12000033", "Aberdeen City", "S13002847", "Kincorth/Nigg/Cove"], "AB125TL": ["57.116163", "-2.116660", "S12000033", "Aberdeen City", "S13002847", "Kincorth/Nigg/Cove"], "AB125TN": ["57.116389", "-2.115240", "S12000033", "Aberdeen City", "S13002847", "Kincorth/Nigg/Cove"], "AB125TP": ["57.115947", "-2.117204", "S12000033", "Aberdeen City", "S13002847", "Kincorth/Nigg/Cove"], "AB125TQ": ["57.115551", "-2.117764", "S12000033", "Aberdeen City", "S13002847", "Kincorth/Nigg/Cove"], "AB125TR": ["57.116540", "-2.117255", "S12000033", "Aberdeen City", "S13002847", "Kincorth/Nigg/Cove"], "AB125TS": ["57.116910", "-2.117909", "S12000033", "Aberdeen City", "S13002847", "Kincorth/Nigg/Cove"], "AB125TT": ["57.118462", "-2.117674", "S12000033", "Aberdeen City", "S13002847", "Kincorth/Nigg/Cove"], "AB125TU": ["57.119863", "-2.117960", "S12000033", "Aberdeen City", "S13002847", "Kincorth/Nigg/Cove"], "AB125TX": ["57.121372", "-2.118130", "S12000033", "Aberdeen City", "S13002847", "Kincorth/Nigg/Cove"], "AB125UA": ["57.120292", "-2.120438", "S12000033", "Aberdeen City", "S13002847", "Kincorth/Nigg/Cove"], "AB125UB": ["57.120185", "-2.119595", "S12000033", "Aberdeen City", "S13002847", "Kincorth/Nigg/Cove"], "AB125UD": ["57.118997", "-2.121342", "S12000033", "Aberdeen City", "S13002847", "Kincorth/Nigg/Cove"], "AB125UE": ["57.115485", "-2.121132", "S12000033", "Aberdeen City", "S13002847", "Kincorth/Nigg/Cove"], "AB125UF": ["57.116698", "-2.121434", "S12000033", "Aberdeen City", "S13002847", "Kincorth/Nigg/Cove"], "AB125UG": ["57.115648", "-2.120159", "S12000033", "Aberdeen City", "S13002847", "Kincorth/Nigg/Cove"], "AB125UH": ["57.116577", "-2.115902", "S12000033", "Aberdeen City", "S13002847", "Kincorth/Nigg/Cove"], "AB125UJ": ["57.119583", "-2.119825", "S12000033", "Aberdeen City", "S13002847", "Kincorth/Nigg/Cove"], "AB125UL": ["57.120303", "-2.118110", "S12000033", "Aberdeen City", "S13002847", "Kincorth/Nigg/Cove"], "AB125UN": ["57.120473", "-2.118721", "S12000033", "Aberdeen City", "S13002847", "Kincorth/Nigg/Cove"], "AB125UP": ["57.118423", "-2.120597", "S12000033", "Aberdeen City", "S13002847", "Kincorth/Nigg/Cove"], "AB125UQ": ["57.118288", "-2.121340", "S12000033", "Aberdeen City", "S13002847", "Kincorth/Nigg/Cove"], "AB125UR": ["57.118406", "-2.119904", "S12000033", "Aberdeen City", "S13002847", "Kincorth/Nigg/Cove"], "AB125US": ["57.121886", "-2.116199", "S12000033", "Aberdeen City", "S13002847", "Kincorth/Nigg/Cove"], "AB125UT": ["57.118047", "-2.119473", "S12000033", "Aberdeen City", "S13002847", "Kincorth/Nigg/Cove"], "AB125UW": ["57.119448", "-2.119659", "S12000033", "Aberdeen City", "S13002847", "Kincorth/Nigg/Cove"], "AB125WA": ["57.111340", "-2.093992", "S12000033", "Aberdeen City", "S13002847", "Kincorth/Nigg/Cove"], "AB125WB": ["57.111340", "-2.093992", "S12000033", "Aberdeen City", "S13002847", "Kincorth/Nigg/Cove"], "AB125WD": ["57.111340", "-2.093992", "S12000033", "Aberdeen City", "S13002847", "Kincorth/Nigg/Cove"], "AB125WE": ["57.111340", "-2.093992", "S12000033", "Aberdeen City", "S13002847", "Kincorth/Nigg/Cove"], "AB125WF": ["57.118056", "-2.119457", "S12000033", "Aberdeen City", "S13002847", "Kincorth/Nigg/Cove"], "AB125WG": ["57.101146", "-2.201873", "S12000034", "Aberdeenshire", "S13002864", "North Kincardine"], "AB125WH": ["57.101386", "-2.202963", "S12000034", "Aberdeenshire", "S13002864", "North Kincardine"], "AB125WJ": ["57.101927", "-2.196314", "S12000034", "Aberdeenshire", "S13002864", "North Kincardine"], "AB125WQ": ["57.111340", "-2.093992", "S12000033", "Aberdeen City", "S13002847", "Kincorth/Nigg/Cove"], "AB125WZ": ["57.111340", "-2.093992", "S12000033", "Aberdeen City", "S13002847", "Kincorth/Nigg/Cove"], "AB125XA": ["57.123538", "-2.116716", "S12000033", "Aberdeen City", "S13002847", "Kincorth/Nigg/Cove"], "AB125XB": ["57.123208", "-2.114849", "S12000033", "Aberdeen City", "S13002847", "Kincorth/Nigg/Cove"], "AB125XD": ["57.110818", "-2.116957", "S12000033", "Aberdeen City", "S13002847", "Kincorth/Nigg/Cove"], "AB125XE": ["57.116577", "-2.115902", "S12000033", "Aberdeen City", "S13002847", "Kincorth/Nigg/Cove"], "AB125XF": ["57.116577", "-2.115902", "S12000033", "Aberdeen City", "S13002847", "Kincorth/Nigg/Cove"], "AB125XG": ["57.111340", "-2.093992", "S12000033", "Aberdeen City", "S13002847", "Kincorth/Nigg/Cove"], "AB125XH": ["57.108312", "-2.106218", "S12000033", "Aberdeen City", "S13002847", "Kincorth/Nigg/Cove"], "AB125XJ": ["57.107934", "-2.116997", "S12000033", "Aberdeen City", "S13002847", "Kincorth/Nigg/Cove"], "AB125XL": ["57.104065", "-2.124116", "S12000034", "Aberdeenshire", "S13002864", "North Kincardine"], "AB125XN": ["57.109523", "-2.127469", "S12000034", "Aberdeenshire", "S13002864", "North Kincardine"], "AB125XP": ["57.107726", "-2.144104", "S12000034", "Aberdeenshire", "S13002864", "North Kincardine"], "AB125XQ": ["57.096240", "-2.135849", "S12000034", "Aberdeenshire", "S13002864", "North Kincardine"], "AB125XR": ["57.102596", "-2.152403", "S12000034", "Aberdeenshire", "S13002864", "North Kincardine"], "AB125XS": ["57.110555", "-2.152601", "S12000034", "Aberdeenshire", "S13002864", "North Kincardine"], "AB125XT": ["57.106502", "-2.168118", "S12000034", "Aberdeenshire", "S13002864", "North Kincardine"], "AB125XU": ["57.099324", "-2.168218", "S12000034", "Aberdeenshire", "S13002864", "North Kincardine"], "AB125XW": ["57.108743", "-2.134697", "S12000034", "Aberdeenshire", "S13002864", "North Kincardine"], "AB125XX": ["57.093784", "-2.166691", "S12000034", "Aberdeenshire", "S13002864", "North Kincardine"], "AB125XY": ["57.093784", "-2.166691", "S12000034", "Aberdeenshire", "S13002864", "North Kincardine"], "AB125YA": ["57.085018", "-2.171816", "S12000034", "Aberdeenshire", "S13002864", "North Kincardine"], "AB125YB": ["57.081072", "-2.182198", "S12000034", "Aberdeenshire", "S13002864", "North Kincardine"], "AB125YD": ["57.091096", "-2.146102", "S12000034", "Aberdeenshire", "S13002864", "North Kincardine"], "AB125YE": ["57.116577", "-2.115902", "S12000033", "Aberdeen City", "S13002847", "Kincorth/Nigg/Cove"], "AB125YF": ["57.091133", "-2.145244", "S12000034", "Aberdeenshire", "S13002864", "North Kincardine"], "AB125YG": ["57.116577", "-2.115902", "S12000033", "Aberdeen City", "S13002847", "Kincorth/Nigg/Cove"], "AB125YH": ["57.116577", "-2.115902", "S12000033", "Aberdeen City", "S13002847", "Kincorth/Nigg/Cove"], "AB125YJ": ["57.095532", "-2.122982", "S12000034", "Aberdeenshire", "S13002864", "North Kincardine"], "AB125YL": ["57.113060", "-2.140962", "S12000034", "Aberdeenshire", "S13002864", "North Kincardine"], "AB125YN": ["57.111030", "-2.167346", "S12000034", "Aberdeenshire", "S13002864", "North Kincardine"], "AB125YP": ["57.102740", "-2.179606", "S12000034", "Aberdeenshire", "S13002864", "North Kincardine"], "AB125YQ": ["57.101219", "-2.199324", "S12000034", "Aberdeenshire", "S13002864", "North Kincardine"], "AB125YR": ["57.095656", "-2.200482", "S12000034", "Aberdeenshire", "S13002864", "North Kincardine"], "AB125YS": ["57.089129", "-2.182552", "S12000034", "Aberdeenshire", "S13002864", "North Kincardine"], "AB125YT": ["57.082299", "-2.200212", "S12000034", "Aberdeenshire", "S13002864", "North Kincardine"], "AB125YU": ["57.116577", "-2.115902", "S12000033", "Aberdeen City", "S13002847", "Kincorth/Nigg/Cove"], "AB125YW": ["57.106890", "-2.173469", "S12000034", "Aberdeenshire", "S13002864", "North Kincardine"], "AB125YX": ["57.069675", "-2.207565", "S12000034", "Aberdeenshire", "S13002864", "North Kincardine"], "AB125ZA": ["57.116577", "-2.115902", "S12000033", "Aberdeen City", "S13002847", "Kincorth/Nigg/Cove"], "AB125ZB": ["57.116568", "-2.115901", "S12000033", "Aberdeen City", "S13002847", "Kincorth/Nigg/Cove"], "AB125ZD": ["57.116577", "-2.115902", "S12000033", "Aberdeen City", "S13002847", "Kincorth/Nigg/Cove"], "AB125ZE": ["57.111340", "-2.093992", "S12000033", "Aberdeen City", "S13002847", "Kincorth/Nigg/Cove"], "AB125ZF": ["57.116568", "-2.115901", "S12000033", "Aberdeen City", "S13002847", "Kincorth/Nigg/Cove"], "AB125ZG": ["57.111340", "-2.093992", "S12000033", "Aberdeen City", "S13002847", "Kincorth/Nigg/Cove"]}