{"CW79AA": ["53.194821", "-2.520723", "E06000050", "Cheshire West and Chester", "E05012250", "Winsford Over & Verdin"], "CW79AB": ["53.194821", "-2.520723", "E06000050", "Cheshire West and Chester", "E05012250", "Winsford Over & Verdin"], "CW79AD": ["53.194821", "-2.520723", "E06000050", "Cheshire West and Chester", "E05012250", "Winsford Over & Verdin"], "CW79AE": ["53.194821", "-2.520723", "E06000050", "Cheshire West and Chester", "E05012250", "Winsford Over & Verdin"], "CW79AF": ["53.194821", "-2.520723", "E06000050", "Cheshire West and Chester", "E05012250", "Winsford Over & Verdin"], "CW79AG": ["53.194821", "-2.520723", "E06000050", "Cheshire West and Chester", "E05012250", "Winsford Over & Verdin"], "CW79AH": ["53.194821", "-2.520723", "E06000050", "Cheshire West and Chester", "E05012250", "Winsford Over & Verdin"], "CW79AJ": ["53.194821", "-2.520723", "E06000050", "Cheshire West and Chester", "E05012250", "Winsford Over & Verdin"], "CW79AL": ["53.194821", "-2.520723", "E06000050", "Cheshire West and Chester", "E05012250", "Winsford Over & Verdin"], "CW79AN": ["53.194821", "-2.520723", "E06000050", "Cheshire West and Chester", "E05012250", "Winsford Over & Verdin"], "CW79AP": ["53.194821", "-2.520723", "E06000050", "Cheshire West and Chester", "E05012250", "Winsford Over & Verdin"], "CW79AQ": ["53.194821", "-2.520723", "E06000050", "Cheshire West and Chester", "E05012250", "Winsford Over & Verdin"], "CW79AR": ["53.194821", "-2.520723", "E06000050", "Cheshire West and Chester", "E05012250", "Winsford Over & Verdin"], "CW79AS": ["53.194821", "-2.520723", "E06000050", "Cheshire West and Chester", "E05012250", "Winsford Over & Verdin"], "CW79AT": ["53.194821", "-2.520723", "E06000050", "Cheshire West and Chester", "E05012250", "Winsford Over & Verdin"], "CW79AU": ["53.194821", "-2.520723", "E06000050", "Cheshire West and Chester", "E05012250", "Winsford Over & Verdin"], "CW79AX": ["53.194821", "-2.520723", "E06000050", "Cheshire West and Chester", "E05012250", "Winsford Over & Verdin"], "CW79AY": ["53.194821", "-2.520723", "E06000050", "Cheshire West and Chester", "E05012250", "Winsford Over & Verdin"], "CW79AZ": ["53.194821", "-2.520723", "E06000050", "Cheshire West and Chester", "E05012250", "Winsford Over & Verdin"], "CW79BA": ["53.194821", "-2.520723", "E06000050", "Cheshire West and Chester", "E05012250", "Winsford Over & Verdin"], "CW79BB": ["53.194821", "-2.520723", "E06000050", "Cheshire West and Chester", "E05012250", "Winsford Over & Verdin"], "CW79BD": ["53.194821", "-2.520723", "E06000050", "Cheshire West and Chester", "E05012250", "Winsford Over & Verdin"], "CW79BE": ["53.194821", "-2.520723", "E06000050", "Cheshire West and Chester", "E05012250", "Winsford Over & Verdin"], "CW79BF": ["53.194821", "-2.520723", "E06000050", "Cheshire West and Chester", "E05012250", "Winsford Over & Verdin"], "CW79BG": ["53.194821", "-2.520723", "E06000050", "Cheshire West and Chester", "E05012250", "Winsford Over & Verdin"], "CW79BH": ["53.194821", "-2.520723", "E06000050", "Cheshire West and Chester", "E05012250", "Winsford Over & Verdin"], "CW79BJ": ["53.194821", "-2.520723", "E06000050", "Cheshire West and Chester", "E05012250", "Winsford Over & Verdin"], "CW79BL": ["53.194821", "-2.520723", "E06000050", "Cheshire West and Chester", "E05012250", "Winsford Over & Verdin"], "CW79BN": ["53.194821", "-2.520723", "E06000050", "Cheshire West and Chester", "E05012250", "Winsford Over & Verdin"], "CW79BP": ["53.194821", "-2.520723", "E06000050", "Cheshire West and Chester", "E05012250", "Winsford Over & Verdin"], "CW79BQ": ["53.194821", "-2.520723", "E06000050", "Cheshire West and Chester", "E05012250", "Winsford Over & Verdin"], "CW79BR": ["53.194821", "-2.520723", "E06000050", "Cheshire West and Chester", "E05012250", "Winsford Over & Verdin"], "CW79BS": ["53.194821", "-2.520723", "E06000050", "Cheshire West and Chester", "E05012250", "Winsford Over & Verdin"], "CW79BT": ["53.194821", "-2.520723", "E06000050", "Cheshire West and Chester", "E05012250", "Winsford Over & Verdin"], "CW79BU": ["53.194821", "-2.520723", "E06000050", "Cheshire West and Chester", "E05012250", "Winsford Over & Verdin"], "CW79BW": ["53.194821", "-2.520723", "E06000050", "Cheshire West and Chester", "E05012250", "Winsford Over & Verdin"], "CW79BX": ["53.194821", "-2.520723", "E06000050", "Cheshire West and Chester", "E05012250", "Winsford Over & Verdin"], "CW79BY": ["53.194821", "-2.520723", "E06000050", "Cheshire West and Chester", "E05012250", "Winsford Over & Verdin"], "CW79BZ": ["53.194821", "-2.520723", "E06000050", "Cheshire West and Chester", "E05012250", "Winsford Over & Verdin"], "CW79DA": ["53.194821", "-2.520723", "E06000050", "Cheshire West and Chester", "E05012250", "Winsford Over & Verdin"], "CW79DB": ["53.194821", "-2.520723", "E06000050", "Cheshire West and Chester", "E05012250", "Winsford Over & Verdin"], "CW79DD": ["53.194821", "-2.520723", "E06000050", "Cheshire West and Chester", "E05012250", "Winsford Over & Verdin"], "CW79DE": ["53.194821", "-2.520723", "E06000050", "Cheshire West and Chester", "E05012250", "Winsford Over & Verdin"], "CW79DF": ["53.194821", "-2.520723", "E06000050", "Cheshire West and Chester", "E05012250", "Winsford Over & Verdin"], "CW79DG": ["53.194794", "-2.520708", "E06000050", "Cheshire West and Chester", "E05012250", "Winsford Over & Verdin"], "CW79DH": ["53.194821", "-2.520723", "E06000050", "Cheshire West and Chester", "E05012250", "Winsford Over & Verdin"], "CW79DJ": ["53.194821", "-2.520723", "E06000050", "Cheshire West and Chester", "E05012250", "Winsford Over & Verdin"], "CW79DL": ["53.194821", "-2.520723", "E06000050", "Cheshire West and Chester", "E05012250", "Winsford Over & Verdin"], "CW79DN": ["53.194821", "-2.520723", "E06000050", "Cheshire West and Chester", "E05012250", "Winsford Over & Verdin"], "CW79DP": ["53.194821", "-2.520723", "E06000050", "Cheshire West and Chester", "E05012250", "Winsford Over & Verdin"], "CW79DQ": ["53.194821", "-2.520723", "E06000050", "Cheshire West and Chester", "E05012250", "Winsford Over & Verdin"], "CW79DR": ["53.194821", "-2.520723", "E06000050", "Cheshire West and Chester", "E05012250", "Winsford Over & Verdin"], "CW79DS": ["53.194821", "-2.520723", "E06000050", "Cheshire West and Chester", "E05012250", "Winsford Over & Verdin"], "CW79DT": ["53.194821", "-2.520723", "E06000050", "Cheshire West and Chester", "E05012250", "Winsford Over & Verdin"], "CW79EA": ["53.194821", "-2.520723", "E06000050", "Cheshire West and Chester", "E05012250", "Winsford Over & Verdin"], "CW79EB": ["53.194821", "-2.520723", "E06000050", "Cheshire West and Chester", "E05012250", "Winsford Over & Verdin"], "CW79ED": ["53.194794", "-2.520708", "E06000050", "Cheshire West and Chester", "E05012250", "Winsford Over & Verdin"], "CW79EE": ["53.194821", "-2.520723", "E06000050", "Cheshire West and Chester", "E05012250", "Winsford Over & Verdin"], "CW79EF": ["53.194821", "-2.520723", "E06000050", "Cheshire West and Chester", "E05012250", "Winsford Over & Verdin"], "CW79EG": ["53.194821", "-2.520723", "E06000050", "Cheshire West and Chester", "E05012250", "Winsford Over & Verdin"], "CW79EH": ["53.194794", "-2.520708", "E06000050", "Cheshire West and Chester", "E05012250", "Winsford Over & Verdin"], "CW79EJ": ["53.194821", "-2.520723", "E06000050", "Cheshire West and Chester", "E05012250", "Winsford Over & Verdin"], "CW79EL": ["53.194821", "-2.520723", "E06000050", "Cheshire West and Chester", "E05012250", "Winsford Over & Verdin"], "CW79EN": ["53.194821", "-2.520723", "E06000050", "Cheshire West and Chester", "E05012250", "Winsford Over & Verdin"], "CW79EP": ["53.194821", "-2.520723", "E06000050", "Cheshire West and Chester", "E05012250", "Winsford Over & Verdin"], "CW79EQ": ["53.194821", "-2.520723", "E06000050", "Cheshire West and Chester", "E05012250", "Winsford Over & Verdin"], "CW79ER": ["53.194821", "-2.520723", "E06000050", "Cheshire West and Chester", "E05012250", "Winsford Over & Verdin"], "CW79ES": ["53.194821", "-2.520723", "E06000050", "Cheshire West and Chester", "E05012250", "Winsford Over & Verdin"], "CW79ET": ["53.194821", "-2.520723", "E06000050", "Cheshire West and Chester", "E05012250", "Winsford Over & Verdin"], "CW79EU": ["53.194821", "-2.520723", "E06000050", "Cheshire West and Chester", "E05012250", "Winsford Over & Verdin"], "CW79EW": ["53.194794", "-2.520708", "E06000050", "Cheshire West and Chester", "E05012250", "Winsford Over & Verdin"], "CW79EX": ["53.194821", "-2.520723", "E06000050", "Cheshire West and Chester", "E05012250", "Winsford Over & Verdin"], "CW79EY": ["53.194821", "-2.520723", "E06000050", "Cheshire West and Chester", "E05012250", "Winsford Over & Verdin"], "CW79EZ": ["53.194821", "-2.520723", "E06000050", "Cheshire West and Chester", "E05012250", "Winsford Over & Verdin"], "CW79FA": ["53.194821", "-2.520723", "E06000050", "Cheshire West and Chester", "E05012250", "Winsford Over & Verdin"], "CW79FB": ["53.194821", "-2.520723", "E06000050", "Cheshire West and Chester", "E05012250", "Winsford Over & Verdin"], "CW79FD": ["53.194821", "-2.520723", "E06000050", "Cheshire West and Chester", "E05012250", "Winsford Over & Verdin"], "CW79FE": ["53.194821", "-2.520723", "E06000050", "Cheshire West and Chester", "E05012250", "Winsford Over & Verdin"], "CW79FF": ["53.194821", "-2.520723", "E06000050", "Cheshire West and Chester", "E05012250", "Winsford Over & Verdin"], "CW79FG": ["53.194821", "-2.520723", "E06000050", "Cheshire West and Chester", "E05012250", "Winsford Over & Verdin"], "CW79FH": ["53.194821", "-2.520723", "E06000050", "Cheshire West and Chester", "E05012250", "Winsford Over & Verdin"], "CW79FJ": ["53.194794", "-2.520708", "E06000050", "Cheshire West and Chester", "E05012250", "Winsford Over & Verdin"], "CW79FL": ["53.194821", "-2.520723", "E06000050", "Cheshire West and Chester", "E05012250", "Winsford Over & Verdin"], "CW79FN": ["53.194794", "-2.520708", "E06000050", "Cheshire West and Chester", "E05012250", "Winsford Over & Verdin"], "CW79FP": ["53.194821", "-2.520723", "E06000050", "Cheshire West and Chester", "E05012250", "Winsford Over & Verdin"], "CW79FQ": ["53.194821", "-2.520723", "E06000050", "Cheshire West and Chester", "E05012250", "Winsford Over & Verdin"], "CW79FR": ["53.194821", "-2.520723", "E06000050", "Cheshire West and Chester", "E05012250", "Winsford Over & Verdin"], "CW79FS": ["53.194821", "-2.520723", "E06000050", "Cheshire West and Chester", "E05012250", "Winsford Over & Verdin"], "CW79FT": ["53.194821", "-2.520723", "E06000050", "Cheshire West and Chester", "E05012250", "Winsford Over & Verdin"], "CW79FU": ["53.194821", "-2.520723", "E06000050", "Cheshire West and Chester", "E05012250", "Winsford Over & Verdin"], "CW79FW": ["53.194794", "-2.520708", "E06000050", "Cheshire West and Chester", "E05012250", "Winsford Over & Verdin"], "CW79FX": ["53.194809", "-2.520707", "E06000050", "Cheshire West and Chester", "E05012250", "Winsford Over & Verdin"], "CW79FY": ["53.194794", "-2.520708", "E06000050", "Cheshire West and Chester", "E05012250", "Winsford Over & Verdin"], "CW79FZ": ["53.194821", "-2.520723", "E06000050", "Cheshire West and Chester", "E05012250", "Winsford Over & Verdin"], "CW79GA": ["53.194794", "-2.520708", "E06000050", "Cheshire West and Chester", "E05012250", "Winsford Over & Verdin"], "CW79GB": ["53.194794", "-2.520708", "E06000050", "Cheshire West and Chester", "E05012250", "Winsford Over & Verdin"], "CW79GD": ["53.194794", "-2.520708", "E06000050", "Cheshire West and Chester", "E05012250", "Winsford Over & Verdin"], "CW79GE": ["53.194821", "-2.520723", "E06000050", "Cheshire West and Chester", "E05012250", "Winsford Over & Verdin"], "CW79GF": ["53.194821", "-2.520723", "E06000050", "Cheshire West and Chester", "E05012250", "Winsford Over & Verdin"], "CW79GG": ["53.194821", "-2.520723", "E06000050", "Cheshire West and Chester", "E05012250", "Winsford Over & Verdin"], "CW79GH": ["53.194794", "-2.520708", "E06000050", "Cheshire West and Chester", "E05012250", "Winsford Over & Verdin"], "CW79GJ": ["53.194821", "-2.520723", "E06000050", "Cheshire West and Chester", "E05012250", "Winsford Over & Verdin"], "CW79GL": ["53.194794", "-2.520708", "E06000050", "Cheshire West and Chester", "E05012250", "Winsford Over & Verdin"], "CW79GN": ["53.194794", "-2.520708", "E06000050", "Cheshire West and Chester", "E05012250", "Winsford Over & Verdin"], "CW79GP": ["53.194794", "-2.520708", "E06000050", "Cheshire West and Chester", "E05012250", "Winsford Over & Verdin"], "CW79GQ": ["53.194821", "-2.520723", "E06000050", "Cheshire West and Chester", "E05012250", "Winsford Over & Verdin"], "CW79GR": ["53.194794", "-2.520708", "E06000050", "Cheshire West and Chester", "E05012250", "Winsford Over & Verdin"], "CW79GS": ["53.194794", "-2.520708", "E06000050", "Cheshire West and Chester", "E05012250", "Winsford Over & Verdin"], "CW79GT": ["53.194794", "-2.520708", "E06000050", "Cheshire West and Chester", "E05012250", "Winsford Over & Verdin"], "CW79GU": ["53.194809", "-2.520707", "E06000050", "Cheshire West and Chester", "E05012250", "Winsford Over & Verdin"], "CW79GW": ["53.194809", "-2.520707", "E06000050", "Cheshire West and Chester", "E05012250", "Winsford Over & Verdin"], "CW79GX": ["53.194809", "-2.520707", "E06000050", "Cheshire West and Chester", "E05012250", "Winsford Over & Verdin"], "CW79GY": ["53.194809", "-2.520707", "E06000050", "Cheshire West and Chester", "E05012250", "Winsford Over & Verdin"], "CW79GZ": ["53.194809", "-2.520707", "E06000050", "Cheshire West and Chester", "E05012250", "Winsford Over & Verdin"], "CW79HA": ["53.194809", "-2.520707", "E06000050", "Cheshire West and Chester", "E05012250", "Winsford Over & Verdin"], "CW79HB": ["53.194809", "-2.520707", "E06000050", "Cheshire West and Chester", "E05012250", "Winsford Over & Verdin"], "CW79HD": ["53.194809", "-2.520707", "E06000050", "Cheshire West and Chester", "E05012250", "Winsford Over & Verdin"], "CW79HE": ["53.194809", "-2.520707", "E06000050", "Cheshire West and Chester", "E05012250", "Winsford Over & Verdin"], "CW79HF": ["53.194809", "-2.520707", "E06000050", "Cheshire West and Chester", "E05012250", "Winsford Over & Verdin"], "CW79HG": ["53.194809", "-2.520707", "E06000050", "Cheshire West and Chester", "E05012250", "Winsford Over & Verdin"], "CW79HH": ["53.194809", "-2.520707", "E06000050", "Cheshire West and Chester", "E05012250", "Winsford Over & Verdin"], "CW79HJ": ["53.194809", "-2.520707", "E06000050", "Cheshire West and Chester", "E05012250", "Winsford Over & Verdin"], "CW79HL": ["53.194809", "-2.520707", "E06000050", "Cheshire West and Chester", "E05012250", "Winsford Over & Verdin"], "CW79HN": ["53.194809", "-2.520707", "E06000050", "Cheshire West and Chester", "E05012250", "Winsford Over & Verdin"], "CW79SA": ["53.189969", "-2.526337", "E06000050", "Cheshire West and Chester", "E05012248", "Winsford Dene"], "CW79SB": ["53.189969", "-2.526337", "E06000050", "Cheshire West and Chester", "E05012248", "Winsford Dene"], "CW79SD": ["53.189969", "-2.526337", "E06000050", "Cheshire West and Chester", "E05012248", "Winsford Dene"], "CW79SE": ["53.189969", "-2.526337", "E06000050", "Cheshire West and Chester", "E05012248", "Winsford Dene"], "CW79SF": ["53.189969", "-2.526337", "E06000050", "Cheshire West and Chester", "E05012248", "Winsford Dene"], "CW79SG": ["53.189969", "-2.526337", "E06000050", "Cheshire West and Chester", "E05012248", "Winsford Dene"], "CW79SH": ["53.189969", "-2.526337", "E06000050", "Cheshire West and Chester", "E05012248", "Winsford Dene"], "CW79SJ": ["53.189969", "-2.526337", "E06000050", "Cheshire West and Chester", "E05012248", "Winsford Dene"], "CW79SL": ["53.189969", "-2.526337", "E06000050", "Cheshire West and Chester", "E05012248", "Winsford Dene"], "CW79SN": ["53.189969", "-2.526337", "E06000050", "Cheshire West and Chester", "E05012248", "Winsford Dene"], "CW79SP": ["53.189969", "-2.526337", "E06000050", "Cheshire West and Chester", "E05012248", "Winsford Dene"], "CW79SQ": ["53.189969", "-2.526337", "E06000050", "Cheshire West and Chester", "E05012248", "Winsford Dene"], "CW79SR": ["53.189969", "-2.526337", "E06000050", "Cheshire West and Chester", "E05012248", "Winsford Dene"], "CW79SS": ["53.189969", "-2.526337", "E06000050", "Cheshire West and Chester", "E05012248", "Winsford Dene"], "CW79ST": ["53.189969", "-2.526337", "E06000050", "Cheshire West and Chester", "E05012248", "Winsford Dene"], "CW79SU": ["53.189969", "-2.526337", "E06000050", "Cheshire West and Chester", "E05012248", "Winsford Dene"], "CW79SW": ["53.189969", "-2.526337", "E06000050", "Cheshire West and Chester", "E05012248", "Winsford Dene"], "CW79SX": ["53.189969", "-2.526337", "E06000050", "Cheshire West and Chester", "E05012248", "Winsford Dene"], "CW79SY": ["53.189969", "-2.526337", "E06000050", "Cheshire West and Chester", "E05012248", "Winsford Dene"], "CW79SZ": ["53.189969", "-2.526337", "E06000050", "Cheshire West and Chester", "E05012248", "Winsford Dene"], "CW79TA": ["53.189969", "-2.526337", "E06000050", "Cheshire West and Chester", "E05012248", "Winsford Dene"], "CW79TB": ["53.189969", "-2.526337", "E06000050", "Cheshire West and Chester", "E05012248", "Winsford Dene"], "CW79TD": ["53.189969", "-2.526337", "E06000050", "Cheshire West and Chester", "E05012248", "Winsford Dene"], "CW79TE": ["53.189969", "-2.526337", "E06000050", "Cheshire West and Chester", "E05012248", "Winsford Dene"], "CW79TF": ["53.189969", "-2.526337", "E06000050", "Cheshire West and Chester", "E05012248", "Winsford Dene"], "CW79TG": ["53.189969", "-2.526337", "E06000050", "Cheshire West and Chester", "E05012248", "Winsford Dene"], "CW79TH": ["53.189969", "-2.526337", "E06000050", "Cheshire West and Chester", "E05012248", "Winsford Dene"], "CW79TJ": ["53.189969", "-2.526337", "E06000050", "Cheshire West and Chester", "E05012248", "Winsford Dene"], "CW79TL": ["53.189969", "-2.526337", "E06000050", "Cheshire West and Chester", "E05012248", "Winsford Dene"], "CW79TN": ["53.189503", "-2.525942", "E06000050", "Cheshire West and Chester", "E05012248", "Winsford Dene"], "CW79TP": ["53.189503", "-2.525942", "E06000050", "Cheshire West and Chester", "E05012248", "Winsford Dene"], "CW79TQ": ["53.189969", "-2.526337", "E06000050", "Cheshire West and Chester", "E05012248", "Winsford Dene"], "CW79TR": ["53.189503", "-2.525942", "E06000050", "Cheshire West and Chester", "E05012248", "Winsford Dene"], "CW79TS": ["53.189503", "-2.525942", "E06000050", "Cheshire West and Chester", "E05012248", "Winsford Dene"], "CW79TT": ["53.189503", "-2.525942", "E06000050", "Cheshire West and Chester", "E05012248", "Winsford Dene"], "CW79TU": ["53.189503", "-2.525942", "E06000050", "Cheshire West and Chester", "E05012248", "Winsford Dene"], "CW79TW": ["53.189503", "-2.525942", "E06000050", "Cheshire West and Chester", "E05012248", "Winsford Dene"], "CW79TX": ["53.189503", "-2.525942", "E06000050", "Cheshire West and Chester", "E05012248", "Winsford Dene"], "CW79TY": ["53.189503", "-2.525942", "E06000050", "Cheshire West and Chester", "E05012248", "Winsford Dene"], "CW79WZ": ["53.194821", "-2.520723", "E06000050", "Cheshire West and Chester", "E05012250", "Winsford Over & Verdin"]}