{"EX144AA": ["50.850792", "-3.227327", "E07000040", "East Devon", "E05011789", "Dunkeswell & Otterhead"], "EX144AB": ["50.853528", "-3.222796", "E07000040", "East Devon", "E05011789", "Dunkeswell & Otterhead"], "EX144AD": ["50.854224", "-3.223314", "E07000040", "East Devon", "E05011789", "Dunkeswell & Otterhead"], "EX144AE": ["50.861186", "-3.223223", "E07000040", "East Devon", "E05011789", "Dunkeswell & Otterhead"], "EX144AF": ["50.856830", "-3.217429", "E07000040", "East Devon", "E05011789", "Dunkeswell & Otterhead"], "EX144AG": ["50.814324", "-3.194506", "E07000040", "East Devon", "E05011789", "Dunkeswell & Otterhead"], "EX144AH": ["50.868418", "-3.237471", "E07000040", "East Devon", "E05011789", "Dunkeswell & Otterhead"], "EX144AJ": ["50.858749", "-3.227493", "E07000040", "East Devon", "E05011789", "Dunkeswell & Otterhead"], "EX144JP": ["50.854286", "-3.223359", "E07000040", "East Devon", "E05011789", "Dunkeswell & Otterhead"], "EX144LA": ["50.863674", "-3.224368", "E07000040", "East Devon", "E05011789", "Dunkeswell & Otterhead"], "EX144LB": ["50.861262", "-3.227846", "E07000040", "East Devon", "E05011789", "Dunkeswell & Otterhead"], "EX144LD": ["50.863583", "-3.225264", "E07000040", "East Devon", "E05011789", "Dunkeswell & Otterhead"], "EX144LE": ["50.861826", "-3.229012", "E07000040", "East Devon", "E05011789", "Dunkeswell & Otterhead"], "EX144LF": ["50.863664", "-3.226091", "E07000040", "East Devon", "E05011789", "Dunkeswell & Otterhead"], "EX144LG": ["50.864253", "-3.227328", "E07000040", "East Devon", "E05011789", "Dunkeswell & Otterhead"], "EX144LH": ["50.859209", "-3.231586", "E07000040", "East Devon", "E05011789", "Dunkeswell & Otterhead"], "EX144LJ": ["50.864490", "-3.227022", "E07000040", "East Devon", "E05011789", "Dunkeswell & Otterhead"], "EX144LL": ["50.862969", "-3.226342", "E07000040", "East Devon", "E05011789", "Dunkeswell & Otterhead"], "EX144LN": ["50.864806", "-3.225197", "E07000040", "East Devon", "E05011789", "Dunkeswell & Otterhead"], "EX144LP": ["50.864860", "-3.224403", "E07000040", "East Devon", "E05011789", "Dunkeswell & Otterhead"], "EX144LT": ["50.865453", "-3.238899", "E07000040", "East Devon", "E05011789", "Dunkeswell & Otterhead"], "EX144PA": ["50.806220", "-3.173333", "E07000040", "East Devon", "E05011798", "Honiton St Paul's"], "EX144PB": ["50.866065", "-3.222711", "E07000040", "East Devon", "E05011789", "Dunkeswell & Otterhead"], "EX144PE": ["50.864772", "-3.223306", "E07000040", "East Devon", "E05011789", "Dunkeswell & Otterhead"], "EX144PF": ["50.864502", "-3.223438", "E07000040", "East Devon", "E05011789", "Dunkeswell & Otterhead"], "EX144PG": ["50.864406", "-3.223908", "E07000040", "East Devon", "E05011789", "Dunkeswell & Otterhead"], "EX144PN": ["50.804482", "-3.182533", "E07000040", "East Devon", "E05011798", "Honiton St Paul's"], "EX144PP": ["50.864820", "-3.223904", "E07000040", "East Devon", "E05011789", "Dunkeswell & Otterhead"], "EX144PQ": ["50.864611", "-3.224155", "E07000040", "East Devon", "E05011789", "Dunkeswell & Otterhead"], "EX144PR": ["50.807087", "-3.169442", "E07000040", "East Devon", "E05011798", "Honiton St Paul's"], "EX144PS": ["50.807111", "-3.171557", "E07000040", "East Devon", "E05011798", "Honiton St Paul's"], "EX144PT": ["50.808009", "-3.170771", "E07000040", "East Devon", "E05011798", "Honiton St Paul's"], "EX144PU": ["50.806878", "-3.172332", "E07000040", "East Devon", "E05011798", "Honiton St Paul's"], "EX144PW": ["50.810248", "-3.174371", "E07000040", "East Devon", "E05011798", "Honiton St Paul's"], "EX144PX": ["50.807111", "-3.171557", "E07000040", "East Devon", "E05011798", "Honiton St Paul's"], "EX144QA": ["50.863196", "-3.220139", "E07000040", "East Devon", "E05011789", "Dunkeswell & Otterhead"], "EX144QD": ["50.854909", "-3.220533", "E07000040", "East Devon", "E05011789", "Dunkeswell & Otterhead"], "EX144QE": ["50.852343", "-3.221702", "E07000040", "East Devon", "E05011789", "Dunkeswell & Otterhead"], "EX144QF": ["50.852199", "-3.220818", "E07000040", "East Devon", "E05011789", "Dunkeswell & Otterhead"], "EX144QG": ["50.857911", "-3.224121", "E07000040", "East Devon", "E05011789", "Dunkeswell & Otterhead"], "EX144QH": ["50.851069", "-3.226595", "E07000040", "East Devon", "E05011789", "Dunkeswell & Otterhead"], "EX144QJ": ["50.849608", "-3.226930", "E07000040", "East Devon", "E05011789", "Dunkeswell & Otterhead"], "EX144QL": ["50.841450", "-3.221983", "E07000040", "East Devon", "E05011789", "Dunkeswell & Otterhead"], "EX144QN": ["50.846102", "-3.238809", "E07000040", "East Devon", "E05011789", "Dunkeswell & Otterhead"], "EX144QP": ["50.860486", "-3.266005", "E07000040", "East Devon", "E05011789", "Dunkeswell & Otterhead"], "EX144QQ": ["50.852452", "-3.219049", "E07000040", "East Devon", "E05011789", "Dunkeswell & Otterhead"], "EX144QR": ["50.859770", "-3.262363", "E07000040", "East Devon", "E05011789", "Dunkeswell & Otterhead"], "EX144QS": ["50.866820", "-3.255732", "E07000040", "East Devon", "E05011789", "Dunkeswell & Otterhead"], "EX144QT": ["50.869178", "-3.253905", "E07000040", "East Devon", "E05011789", "Dunkeswell & Otterhead"], "EX144QU": ["50.870318", "-3.251605", "E07000040", "East Devon", "E05011789", "Dunkeswell & Otterhead"], "EX144QW": ["50.854496", "-3.261112", "E07000040", "East Devon", "E05011789", "Dunkeswell & Otterhead"], "EX144QX": ["50.872226", "-3.243029", "E07000040", "East Devon", "E05011789", "Dunkeswell & Otterhead"], "EX144QY": ["50.855993", "-3.245649", "E07000040", "East Devon", "E05011789", "Dunkeswell & Otterhead"], "EX144QZ": ["50.863065", "-3.221428", "E07000040", "East Devon", "E05011789", "Dunkeswell & Otterhead"], "EX144RA": ["50.855946", "-3.237382", "E07000040", "East Devon", "E05011789", "Dunkeswell & Otterhead"], "EX144RB": ["50.864955", "-3.225652", "E07000040", "East Devon", "E05011789", "Dunkeswell & Otterhead"], "EX144RD": ["50.866385", "-3.223999", "E07000040", "East Devon", "E05011789", "Dunkeswell & Otterhead"], "EX144RE": ["50.860753", "-3.223300", "E07000040", "East Devon", "E05011789", "Dunkeswell & Otterhead"], "EX144RF": ["50.861363", "-3.222592", "E07000040", "East Devon", "E05011789", "Dunkeswell & Otterhead"], "EX144RG": ["50.862109", "-3.219158", "E07000040", "East Devon", "E05011789", "Dunkeswell & Otterhead"], "EX144RH": ["50.864461", "-3.213465", "E07000040", "East Devon", "E05011789", "Dunkeswell & Otterhead"], "EX144RJ": ["50.865158", "-3.223444", "E07000040", "East Devon", "E05011789", "Dunkeswell & Otterhead"], "EX144RL": ["50.864208", "-3.220506", "E07000040", "East Devon", "E05011789", "Dunkeswell & Otterhead"], "EX144RN": ["50.877800", "-3.222766", "E07000040", "East Devon", "E05011789", "Dunkeswell & Otterhead"], "EX144RP": ["50.887731", "-3.224178", "E07000040", "East Devon", "E05011789", "Dunkeswell & Otterhead"], "EX144RQ": ["50.860041", "-3.217385", "E07000040", "East Devon", "E05011789", "Dunkeswell & Otterhead"], "EX144RR": ["50.881579", "-3.225097", "E07000040", "East Devon", "E05011789", "Dunkeswell & Otterhead"], "EX144RS": ["50.867258", "-3.222106", "E07000040", "East Devon", "E05011789", "Dunkeswell & Otterhead"], "EX144RT": ["50.852586", "-3.180652", "E07000040", "East Devon", "E05011789", "Dunkeswell & Otterhead"], "EX144RU": ["50.850439", "-3.176848", "E07000040", "East Devon", "E05011789", "Dunkeswell & Otterhead"], "EX144RW": ["50.882165", "-3.231876", "E07000040", "East Devon", "E05011789", "Dunkeswell & Otterhead"], "EX144RX": ["50.855660", "-3.179025", "E07000040", "East Devon", "E05011789", "Dunkeswell & Otterhead"], "EX144RY": ["50.854757", "-3.182085", "E07000040", "East Devon", "E05011789", "Dunkeswell & Otterhead"], "EX144RZ": ["50.863639", "-3.179624", "E07000040", "East Devon", "E05011789", "Dunkeswell & Otterhead"], "EX144SA": ["50.866422", "-3.167725", "E07000040", "East Devon", "E05011789", "Dunkeswell & Otterhead"], "EX144SB": ["50.856175", "-3.172559", "E07000040", "East Devon", "E05011789", "Dunkeswell & Otterhead"], "EX144SD": ["50.888967", "-3.229894", "E07000040", "East Devon", "E05011789", "Dunkeswell & Otterhead"], "EX144SE": ["50.880404", "-3.238567", "E07000040", "East Devon", "E05011789", "Dunkeswell & Otterhead"], "EX144SF": ["50.831054", "-3.215992", "E07000040", "East Devon", "E05011789", "Dunkeswell & Otterhead"], "EX144SG": ["50.826817", "-3.215212", "E07000040", "East Devon", "E05011789", "Dunkeswell & Otterhead"], "EX144SH": ["50.860769", "-3.208847", "E07000040", "East Devon", "E05011789", "Dunkeswell & Otterhead"], "EX144SJ": ["50.848977", "-3.175618", "E07000040", "East Devon", "E05011789", "Dunkeswell & Otterhead"], "EX144SL": ["50.847765", "-3.173623", "E07000040", "East Devon", "E05011789", "Dunkeswell & Otterhead"], "EX144SN": ["50.844910", "-3.173072", "E07000040", "East Devon", "E05011789", "Dunkeswell & Otterhead"], "EX144SP": ["50.876748", "-3.162141", "E07000040", "East Devon", "E05011789", "Dunkeswell & Otterhead"], "EX144SQ": ["50.839225", "-3.222325", "E07000040", "East Devon", "E05011789", "Dunkeswell & Otterhead"], "EX144SR": ["50.878548", "-3.178011", "E07000042", "Mid Devon", "E05003528", "Upper Culm"], "EX144SS": ["50.872978", "-3.192495", "E07000040", "East Devon", "E05011789", "Dunkeswell & Otterhead"], "EX144ST": ["50.868441", "-3.199115", "E07000040", "East Devon", "E05011789", "Dunkeswell & Otterhead"], "EX144SU": ["50.855226", "-3.188107", "E07000040", "East Devon", "E05011789", "Dunkeswell & Otterhead"], "EX144SW": ["50.850393", "-3.170695", "E07000040", "East Devon", "E05011789", "Dunkeswell & Otterhead"], "EX144SX": ["50.848849", "-3.191723", "E07000040", "East Devon", "E05011789", "Dunkeswell & Otterhead"], "EX144SY": ["50.851580", "-3.197344", "E07000040", "East Devon", "E05011789", "Dunkeswell & Otterhead"], "EX144SZ": ["50.852672", "-3.209192", "E07000040", "East Devon", "E05011789", "Dunkeswell & Otterhead"], "EX144TA": ["50.840813", "-3.203687", "E07000040", "East Devon", "E05011789", "Dunkeswell & Otterhead"], "EX144TB": ["50.844562", "-3.214209", "E07000040", "East Devon", "E05011789", "Dunkeswell & Otterhead"], "EX144TD": ["50.819593", "-3.183962", "E07000040", "East Devon", "E05011789", "Dunkeswell & Otterhead"], "EX144TG": ["50.810195", "-3.195508", "E07000040", "East Devon", "E05011789", "Dunkeswell & Otterhead"], "EX144TH": ["50.815687", "-3.192241", "E07000040", "East Devon", "E05011789", "Dunkeswell & Otterhead"], "EX144TJ": ["50.816050", "-3.191072", "E07000040", "East Devon", "E05011789", "Dunkeswell & Otterhead"], "EX144TL": ["50.816192", "-3.190363", "E07000040", "East Devon", "E05011789", "Dunkeswell & Otterhead"], "EX144TN": ["50.818958", "-3.183637", "E07000040", "East Devon", "E05011789", "Dunkeswell & Otterhead"], "EX144TP": ["50.820510", "-3.171538", "E07000040", "East Devon", "E05011789", "Dunkeswell & Otterhead"], "EX144TQ": ["50.815362", "-3.193269", "E07000040", "East Devon", "E05011789", "Dunkeswell & Otterhead"], "EX144TR": ["50.831331", "-3.159597", "E07000040", "East Devon", "E05011789", "Dunkeswell & Otterhead"], "EX144TS": ["50.843554", "-3.153110", "E07000040", "East Devon", "E05011789", "Dunkeswell & Otterhead"], "EX144TT": ["50.840759", "-3.164674", "E07000040", "East Devon", "E05011789", "Dunkeswell & Otterhead"], "EX144TU": ["50.841014", "-3.166995", "E07000040", "East Devon", "E05011789", "Dunkeswell & Otterhead"], "EX144TW": ["50.812330", "-3.181922", "E07000040", "East Devon", "E05011789", "Dunkeswell & Otterhead"], "EX144TX": ["50.839411", "-3.167267", "E07000040", "East Devon", "E05011789", "Dunkeswell & Otterhead"], "EX144TY": ["50.830642", "-3.178096", "E07000040", "East Devon", "E05011789", "Dunkeswell & Otterhead"], "EX144TZ": ["50.838620", "-3.177952", "E07000040", "East Devon", "E05011789", "Dunkeswell & Otterhead"], "EX144UA": ["50.842007", "-3.177417", "E07000040", "East Devon", "E05011789", "Dunkeswell & Otterhead"], "EX144UB": ["50.841307", "-3.182593", "E07000040", "East Devon", "E05011789", "Dunkeswell & Otterhead"], "EX144UD": ["50.843884", "-3.185627", "E07000040", "East Devon", "E05011789", "Dunkeswell & Otterhead"], "EX144UE": ["50.841396", "-3.188835", "E07000040", "East Devon", "E05011789", "Dunkeswell & Otterhead"], "EX144UF": ["50.834364", "-3.193200", "E07000040", "East Devon", "E05011789", "Dunkeswell & Otterhead"], "EX144UG": ["50.821850", "-3.186677", "E07000040", "East Devon", "E05011789", "Dunkeswell & Otterhead"], "EX144UH": ["50.823202", "-3.198677", "E07000040", "East Devon", "E05011789", "Dunkeswell & Otterhead"], "EX144UJ": ["50.831298", "-3.208060", "E07000040", "East Devon", "E05011789", "Dunkeswell & Otterhead"], "EX144UL": ["50.818287", "-3.195658", "E07000040", "East Devon", "E05011789", "Dunkeswell & Otterhead"], "EX144UQ": ["50.821689", "-3.198045", "E07000040", "East Devon", "E05011789", "Dunkeswell & Otterhead"], "EX144UR": ["50.854009", "-3.224942", "E07000040", "East Devon", "E05011789", "Dunkeswell & Otterhead"], "EX144UT": ["50.852631", "-3.225972", "E07000040", "East Devon", "E05011789", "Dunkeswell & Otterhead"], "EX144UU": ["50.853026", "-3.224334", "E07000040", "East Devon", "E05011789", "Dunkeswell & Otterhead"], "EX144UX": ["50.852249", "-3.224626", "E07000040", "East Devon", "E05011789", "Dunkeswell & Otterhead"], "EX144UY": ["50.851699", "-3.224797", "E07000040", "East Devon", "E05011789", "Dunkeswell & Otterhead"], "EX144UZ": ["50.851584", "-3.225518", "E07000040", "East Devon", "E05011789", "Dunkeswell & Otterhead"], "EX144WZ": ["50.799361", "-3.187285", "E07000040", "East Devon", "E05011798", "Honiton St Paul's"], "EX144XA": ["50.853109", "-3.223282", "E07000040", "East Devon", "E05011789", "Dunkeswell & Otterhead"], "EX144XB": ["50.852320", "-3.222185", "E07000040", "East Devon", "E05011789", "Dunkeswell & Otterhead"], "EX144XD": ["50.852371", "-3.223280", "E07000040", "East Devon", "E05011789", "Dunkeswell & Otterhead"], "EX144XE": ["50.856215", "-3.220312", "E07000040", "East Devon", "E05011789", "Dunkeswell & Otterhead"], "EX144XF": ["50.855898", "-3.220559", "E07000040", "East Devon", "E05011789", "Dunkeswell & Otterhead"], "EX144XG": ["50.857068", "-3.220533", "E07000040", "East Devon", "E05011789", "Dunkeswell & Otterhead"], "EX144XH": ["50.855462", "-3.223588", "E07000040", "East Devon", "E05011789", "Dunkeswell & Otterhead"], "EX144XJ": ["50.855171", "-3.221279", "E07000040", "East Devon", "E05011789", "Dunkeswell & Otterhead"], "EX144XL": ["50.852992", "-3.219006", "E07000040", "East Devon", "E05011789", "Dunkeswell & Otterhead"], "EX144XN": ["50.853693", "-3.220786", "E07000040", "East Devon", "E05011789", "Dunkeswell & Otterhead"], "EX144XP": ["50.855711", "-3.222117", "E07000040", "East Devon", "E05011789", "Dunkeswell & Otterhead"], "EX144XQ": ["50.862303", "-3.223796", "E07000040", "East Devon", "E05011789", "Dunkeswell & Otterhead"], "EX144XR": ["50.855003", "-3.222752", "E07000040", "East Devon", "E05011789", "Dunkeswell & Otterhead"], "EX144XS": ["50.856375", "-3.222248", "E07000040", "East Devon", "E05011789", "Dunkeswell & Otterhead"], "EX144XT": ["50.854477", "-3.219712", "E07000040", "East Devon", "E05011789", "Dunkeswell & Otterhead"], "EX144XU": ["50.854022", "-3.220283", "E07000040", "East Devon", "E05011789", "Dunkeswell & Otterhead"], "EX144XW": ["50.853453", "-3.220453", "E07000040", "East Devon", "E05011789", "Dunkeswell & Otterhead"], "EX144XX": ["50.853010", "-3.217284", "E07000040", "East Devon", "E05011789", "Dunkeswell & Otterhead"], "EX144XY": ["50.853410", "-3.222000", "E07000040", "East Devon", "E05011789", "Dunkeswell & Otterhead"], "EX144XZ": ["50.853751", "-3.222109", "E07000040", "East Devon", "E05011789", "Dunkeswell & Otterhead"], "EX144YN": ["50.799361", "-3.187285", "E07000040", "East Devon", "E05011798", "Honiton St Paul's"], "EX144YP": ["50.799361", "-3.187285", "E07000040", "East Devon", "E05011798", "Honiton St Paul's"], "EX144YT": ["50.798879", "-3.190465", "E07000040", "East Devon", "E05011797", "Honiton St Michael's"], "EX144YU": ["50.799361", "-3.187285", "E07000040", "East Devon", "E05011798", "Honiton St Paul's"], "EX144YX": ["50.798879", "-3.190465", "E07000040", "East Devon", "E05011797", "Honiton St Michael's"], "EX144YY": ["50.799361", "-3.187285", "E07000040", "East Devon", "E05011798", "Honiton St Paul's"], "EX144YZ": ["50.799361", "-3.187285", "E07000040", "East Devon", "E05011798", "Honiton St Paul's"], "EX144ZN": ["50.799361", "-3.187285", "E07000040", "East Devon", "E05011798", "Honiton St Paul's"], "EX144ZU": ["50.794034", "-3.206883", "E07000040", "East Devon", "E05011797", "Honiton St Michael's"], "EX144ZX": ["50.799361", "-3.187285", "E07000040", "East Devon", "E05011798", "Honiton St Paul's"]}