{"KA300AE": ["55.794251", "-4.867627", "S12000021", "North Ayrshire", "S13003039", "North Coast and Cumbraes"], "KA300AG": ["55.794055", "-4.867150", "S12000021", "North Ayrshire", "S13003039", "North Coast and Cumbraes"], "KA300AH": ["55.794055", "-4.867150", "S12000021", "North Ayrshire", "S13003039", "North Coast and Cumbraes"], "KA300AJ": ["55.794055", "-4.867150", "S12000021", "North Ayrshire", "S13003039", "North Coast and Cumbraes"], "KA300AL": ["55.794055", "-4.867150", "S12000021", "North Ayrshire", "S13003039", "North Coast and Cumbraes"], "KA300AN": ["55.794055", "-4.867150", "S12000021", "North Ayrshire", "S13003039", "North Coast and Cumbraes"], "KA300AP": ["55.794246", "-4.867607", "S12000021", "North Ayrshire", "S13003039", "North Coast and Cumbraes"], "KA300AQ": ["55.794055", "-4.867150", "S12000021", "North Ayrshire", "S13003039", "North Coast and Cumbraes"], "KA300AR": ["55.794251", "-4.867627", "S12000021", "North Ayrshire", "S13003039", "North Coast and Cumbraes"], "KA300AS": ["55.794246", "-4.867607", "S12000021", "North Ayrshire", "S13003039", "North Coast and Cumbraes"], "KA300AT": ["55.794246", "-4.867607", "S12000021", "North Ayrshire", "S13003039", "North Coast and Cumbraes"], "KA300AU": ["55.794246", "-4.867607", "S12000021", "North Ayrshire", "S13003039", "North Coast and Cumbraes"], "KA300AW": ["55.794246", "-4.867607", "S12000021", "North Ayrshire", "S13003039", "North Coast and Cumbraes"], "KA300AX": ["55.794246", "-4.867607", "S12000021", "North Ayrshire", "S13003039", "North Coast and Cumbraes"]}