{"PH107AA": ["56.592542", "-3.334048", "S12000048", "Perth and Kinross", "S13003065", "Blairgowrie and Glens"], "PH107AB": ["56.593758", "-3.332919", "S12000048", "Perth and Kinross", "S13003065", "Blairgowrie and Glens"], "PH107AD": ["56.593889", "-3.333233", "S12000048", "Perth and Kinross", "S13003065", "Blairgowrie and Glens"], "PH107AE": ["56.594409", "-3.334196", "S12000048", "Perth and Kinross", "S13003065", "Blairgowrie and Glens"], "PH107AF": ["56.595552", "-3.335653", "S12000048", "Perth and Kinross", "S13003065", "Blairgowrie and Glens"], "PH107AG": ["56.596993", "-3.335362", "S12000048", "Perth and Kinross", "S13003065", "Blairgowrie and Glens"], "PH107AH": ["56.597750", "-3.337685", "S12000048", "Perth and Kinross", "S13003065", "Blairgowrie and Glens"], "PH107AJ": ["56.598424", "-3.335933", "S12000048", "Perth and Kinross", "S13003065", "Blairgowrie and Glens"], "PH107AL": ["56.599011", "-3.334814", "S12000048", "Perth and Kinross", "S13003065", "Blairgowrie and Glens"], "PH107AN": ["56.598395", "-3.333685", "S12000048", "Perth and Kinross", "S13003065", "Blairgowrie and Glens"], "PH107AP": ["56.597647", "-3.330498", "S12000048", "Perth and Kinross", "S13003065", "Blairgowrie and Glens"], "PH107AQ": ["56.597728", "-3.333058", "S12000048", "Perth and Kinross", "S13003065", "Blairgowrie and Glens"], "PH107AR": ["56.597040", "-3.330949", "S12000048", "Perth and Kinross", "S13003065", "Blairgowrie and Glens"], "PH107AS": ["56.596581", "-3.330184", "S12000048", "Perth and Kinross", "S13003065", "Blairgowrie and Glens"], "PH107AT": ["56.596088", "-3.330069", "S12000048", "Perth and Kinross", "S13003065", "Blairgowrie and Glens"], "PH107AU": ["56.596596", "-3.328816", "S12000048", "Perth and Kinross", "S13003065", "Blairgowrie and Glens"], "PH107AW": ["56.597014", "-3.332593", "S12000048", "Perth and Kinross", "S13003065", "Blairgowrie and Glens"], "PH107AX": ["56.597069", "-3.329094", "S12000048", "Perth and Kinross", "S13003065", "Blairgowrie and Glens"], "PH107AY": ["56.598003", "-3.328345", "S12000048", "Perth and Kinross", "S13003065", "Blairgowrie and Glens"], "PH107AZ": ["56.598284", "-3.325521", "S12000048", "Perth and Kinross", "S13003065", "Blairgowrie and Glens"], "PH107BA": ["56.597898", "-3.326370", "S12000048", "Perth and Kinross", "S13003065", "Blairgowrie and Glens"], "PH107BB": ["56.602228", "-3.340710", "S12000048", "Perth and Kinross", "S13003065", "Blairgowrie and Glens"], "PH107BD": ["56.597112", "-3.337646", "S12000048", "Perth and Kinross", "S13003065", "Blairgowrie and Glens"], "PH107BE": ["56.595996", "-3.331988", "S12000048", "Perth and Kinross", "S13003065", "Blairgowrie and Glens"], "PH107BG": ["56.591979", "-3.334566", "S12000048", "Perth and Kinross", "S13003065", "Blairgowrie and Glens"], "PH107BH": ["56.592152", "-3.334230", "S12000048", "Perth and Kinross", "S13003065", "Blairgowrie and Glens"], "PH107BJ": ["56.591332", "-3.332931", "S12000048", "Perth and Kinross", "S13003065", "Blairgowrie and Glens"], "PH107BL": ["56.591154", "-3.331068", "S12000048", "Perth and Kinross", "S13003065", "Blairgowrie and Glens"], "PH107BN": ["56.589093", "-3.331370", "S12000048", "Perth and Kinross", "S13003065", "Blairgowrie and Glens"], "PH107BP": ["56.590139", "-3.331000", "S12000048", "Perth and Kinross", "S13003065", "Blairgowrie and Glens"], "PH107BQ": ["56.591797", "-3.333078", "S12000048", "Perth and Kinross", "S13003065", "Blairgowrie and Glens"], "PH107BS": ["56.592088", "-3.331101", "S12000048", "Perth and Kinross", "S13003065", "Blairgowrie and Glens"], "PH107BT": ["56.593737", "-3.331517", "S12000048", "Perth and Kinross", "S13003065", "Blairgowrie and Glens"], "PH107BU": ["56.593343", "-3.331406", "S12000048", "Perth and Kinross", "S13003065", "Blairgowrie and Glens"], "PH107BW": ["56.593042", "-3.331835", "S12000048", "Perth and Kinross", "S13003065", "Blairgowrie and Glens"], "PH107BX": ["56.593437", "-3.330139", "S12000048", "Perth and Kinross", "S13003065", "Blairgowrie and Glens"], "PH107BY": ["56.593056", "-3.330500", "S12000048", "Perth and Kinross", "S13003065", "Blairgowrie and Glens"], "PH107BZ": ["56.593616", "-3.329331", "S12000048", "Perth and Kinross", "S13003065", "Blairgowrie and Glens"], "PH107DA": ["56.593172", "-3.328843", "S12000048", "Perth and Kinross", "S13003065", "Blairgowrie and Glens"], "PH107DB": ["56.594182", "-3.328520", "S12000048", "Perth and Kinross", "S13003065", "Blairgowrie and Glens"], "PH107DD": ["56.593711", "-3.327184", "S12000048", "Perth and Kinross", "S13003065", "Blairgowrie and Glens"], "PH107DE": ["56.594250", "-3.329598", "S12000048", "Perth and Kinross", "S13003065", "Blairgowrie and Glens"], "PH107DF": ["56.593964", "-3.329636", "S12000048", "Perth and Kinross", "S13003065", "Blairgowrie and Glens"], "PH107DG": ["56.595751", "-3.326279", "S12000048", "Perth and Kinross", "S13003065", "Blairgowrie and Glens"], "PH107DH": ["56.594033", "-3.321447", "S12000048", "Perth and Kinross", "S13003065", "Blairgowrie and Glens"], "PH107DJ": ["56.595331", "-3.323560", "S12000048", "Perth and Kinross", "S13003065", "Blairgowrie and Glens"], "PH107DL": ["56.596142", "-3.323361", "S12000048", "Perth and Kinross", "S13003065", "Blairgowrie and Glens"], "PH107DN": ["56.595751", "-3.322907", "S12000048", "Perth and Kinross", "S13003065", "Blairgowrie and Glens"], "PH107DP": ["56.596708", "-3.322517", "S12000048", "Perth and Kinross", "S13003065", "Blairgowrie and Glens"], "PH107DQ": ["56.595027", "-3.327687", "S12000048", "Perth and Kinross", "S13003065", "Blairgowrie and Glens"], "PH107DR": ["56.596620", "-3.321505", "S12000048", "Perth and Kinross", "S13003065", "Blairgowrie and Glens"], "PH107DS": ["56.597433", "-3.321924", "S12000048", "Perth and Kinross", "S13003065", "Blairgowrie and Glens"], "PH107DT": ["56.598040", "-3.323167", "S12000048", "Perth and Kinross", "S13003065", "Blairgowrie and Glens"], "PH107DU": ["56.598124", "-3.321851", "S12000048", "Perth and Kinross", "S13003065", "Blairgowrie and Glens"], "PH107DW": ["56.596699", "-3.322517", "S12000048", "Perth and Kinross", "S13003065", "Blairgowrie and Glens"], "PH107DX": ["56.597301", "-3.321464", "S12000048", "Perth and Kinross", "S13003065", "Blairgowrie and Glens"], "PH107DY": ["56.596221", "-3.319259", "S12000048", "Perth and Kinross", "S13003065", "Blairgowrie and Glens"], "PH107DZ": ["56.595999", "-3.321564", "S12000048", "Perth and Kinross", "S13003065", "Blairgowrie and Glens"], "PH107EA": ["56.595903", "-3.322164", "S12000048", "Perth and Kinross", "S13003065", "Blairgowrie and Glens"], "PH107EB": ["56.595028", "-3.321531", "S12000048", "Perth and Kinross", "S13003065", "Blairgowrie and Glens"], "PH107ED": ["56.598356", "-3.330572", "S12000048", "Perth and Kinross", "S13003065", "Blairgowrie and Glens"], "PH107EE": ["56.601655", "-3.339615", "S12000048", "Perth and Kinross", "S13003065", "Blairgowrie and Glens"], "PH107EF": ["56.599609", "-3.337783", "S12000048", "Perth and Kinross", "S13003065", "Blairgowrie and Glens"], "PH107EG": ["56.591801", "-3.331921", "S12000048", "Perth and Kinross", "S13003065", "Blairgowrie and Glens"], "PH107EH": ["56.594510", "-3.335665", "S12000048", "Perth and Kinross", "S13003065", "Blairgowrie and Glens"], "PH107EJ": ["56.594576", "-3.332899", "S12000048", "Perth and Kinross", "S13003065", "Blairgowrie and Glens"], "PH107EL": ["56.595202", "-3.334012", "S12000048", "Perth and Kinross", "S13003065", "Blairgowrie and Glens"], "PH107EN": ["56.595285", "-3.332891", "S12000048", "Perth and Kinross", "S13003065", "Blairgowrie and Glens"], "PH107EP": ["56.594399", "-3.331736", "S12000048", "Perth and Kinross", "S13003065", "Blairgowrie and Glens"], "PH107EQ": ["56.591486", "-3.331992", "S12000048", "Perth and Kinross", "S13003065", "Blairgowrie and Glens"], "PH107ER": ["56.588728", "-3.307177", "S12000048", "Perth and Kinross", "S13003065", "Blairgowrie and Glens"], "PH107ES": ["56.588456", "-3.328775", "S12000048", "Perth and Kinross", "S13003065", "Blairgowrie and Glens"], "PH107ET": ["56.588895", "-3.326380", "S12000048", "Perth and Kinross", "S13003065", "Blairgowrie and Glens"], "PH107EU": ["56.587544", "-3.325845", "S12000048", "Perth and Kinross", "S13003065", "Blairgowrie and Glens"], "PH107EW": ["56.595450", "-3.331806", "S12000048", "Perth and Kinross", "S13003065", "Blairgowrie and Glens"], "PH107EX": ["56.588352", "-3.314931", "S12000048", "Perth and Kinross", "S13003065", "Blairgowrie and Glens"], "PH107EY": ["56.589192", "-3.320220", "S12000048", "Perth and Kinross", "S13003065", "Blairgowrie and Glens"], "PH107EZ": ["56.593038", "-3.318530", "S12000048", "Perth and Kinross", "S13003065", "Blairgowrie and Glens"], "PH107FB": ["56.597281", "-3.325111", "S12000048", "Perth and Kinross", "S13003065", "Blairgowrie and Glens"], "PH107FD": ["56.596854", "-3.324705", "S12000048", "Perth and Kinross", "S13003065", "Blairgowrie and Glens"], "PH107FE": ["56.596314", "-3.326608", "S12000048", "Perth and Kinross", "S13003065", "Blairgowrie and Glens"], "PH107FF": ["56.598671", "-3.329558", "S12000048", "Perth and Kinross", "S13003065", "Blairgowrie and Glens"], "PH107FG": ["56.598923", "-3.330332", "S12000048", "Perth and Kinross", "S13003065", "Blairgowrie and Glens"], "PH107FH": ["56.598901", "-3.329859", "S12000048", "Perth and Kinross", "S13003065", "Blairgowrie and Glens"], "PH107FJ": ["56.598978", "-3.331099", "S12000048", "Perth and Kinross", "S13003065", "Blairgowrie and Glens"], "PH107FL": ["56.598767", "-3.323844", "S12000048", "Perth and Kinross", "S13003065", "Blairgowrie and Glens"], "PH107FN": ["56.594542", "-3.332539", "S12000048", "Perth and Kinross", "S13003065", "Blairgowrie and Glens"], "PH107GA": ["56.595162", "-3.336649", "S12000048", "Perth and Kinross", "S13003065", "Blairgowrie and Glens"], "PH107HA": ["56.594639", "-3.321093", "S12000048", "Perth and Kinross", "S13003065", "Blairgowrie and Glens"], "PH107HB": ["56.604185", "-3.321476", "S12000048", "Perth and Kinross", "S13003065", "Blairgowrie and Glens"], "PH107HD": ["56.608136", "-3.309835", "S12000048", "Perth and Kinross", "S13003065", "Blairgowrie and Glens"], "PH107HE": ["56.615501", "-3.282518", "S12000048", "Perth and Kinross", "S13003064", "Strathmore"], "PH107HF": ["56.597458", "-3.312820", "S12000048", "Perth and Kinross", "S13003065", "Blairgowrie and Glens"], "PH107HG": ["56.592926", "-3.287356", "S12000048", "Perth and Kinross", "S13003065", "Blairgowrie and Glens"], "PH107HH": ["56.600837", "-3.268567", "S12000048", "Perth and Kinross", "S13003064", "Strathmore"], "PH107HJ": ["56.593443", "-3.259672", "S12000048", "Perth and Kinross", "S13003064", "Strathmore"], "PH107HL": ["56.596393", "-3.334298", "S12000048", "Perth and Kinross", "S13003065", "Blairgowrie and Glens"], "PH107HQ": ["56.600995", "-3.277694", "S12000048", "Perth and Kinross", "S13003065", "Blairgowrie and Glens"], "PH107HR": ["56.608778", "-3.343989", "S12000048", "Perth and Kinross", "S13003065", "Blairgowrie and Glens"], "PH107HS": ["56.593474", "-3.334244", "S12000048", "Perth and Kinross", "S13003065", "Blairgowrie and Glens"], "PH107HT": ["56.600213", "-3.340932", "S12000048", "Perth and Kinross", "S13003065", "Blairgowrie and Glens"], "PH107HU": ["56.600811", "-3.339568", "S12000048", "Perth and Kinross", "S13003065", "Blairgowrie and Glens"], "PH107HW": ["56.600061", "-3.340829", "S12000048", "Perth and Kinross", "S13003065", "Blairgowrie and Glens"], "PH107HX": ["56.601175", "-3.340787", "S12000048", "Perth and Kinross", "S13003065", "Blairgowrie and Glens"], "PH107HY": ["56.606125", "-3.345866", "S12000048", "Perth and Kinross", "S13003065", "Blairgowrie and Glens"], "PH107HZ": ["56.600382", "-3.337713", "S12000048", "Perth and Kinross", "S13003065", "Blairgowrie and Glens"], "PH107JA": ["56.603490", "-3.335314", "S12000048", "Perth and Kinross", "S13003065", "Blairgowrie and Glens"], "PH107JB": ["56.617333", "-3.335477", "S12000048", "Perth and Kinross", "S13003065", "Blairgowrie and Glens"], "PH107JD": ["56.638597", "-3.347462", "S12000048", "Perth and Kinross", "S13003065", "Blairgowrie and Glens"], "PH107JE": ["56.609744", "-3.333303", "S12000048", "Perth and Kinross", "S13003065", "Blairgowrie and Glens"], "PH107JG": ["56.646766", "-3.407378", "S12000048", "Perth and Kinross", "S13003065", "Blairgowrie and Glens"], "PH107JH": ["56.654059", "-3.441367", "S12000048", "Perth and Kinross", "S13003065", "Blairgowrie and Glens"], "PH107JJ": ["56.645793", "-3.402808", "S12000048", "Perth and Kinross", "S13003065", "Blairgowrie and Glens"], "PH107JL": ["56.648621", "-3.402016", "S12000048", "Perth and Kinross", "S13003065", "Blairgowrie and Glens"], "PH107JN": ["56.654191", "-3.397427", "S12000048", "Perth and Kinross", "S13003065", "Blairgowrie and Glens"], "PH107JP": ["56.652953", "-3.388443", "S12000048", "Perth and Kinross", "S13003065", "Blairgowrie and Glens"], "PH107JQ": ["56.646318", "-3.421452", "S12000048", "Perth and Kinross", "S13003065", "Blairgowrie and Glens"], "PH107JR": ["56.646336", "-3.364438", "S12000048", "Perth and Kinross", "S13003065", "Blairgowrie and Glens"], "PH107JS": ["56.645603", "-3.343293", "S12000048", "Perth and Kinross", "S13003065", "Blairgowrie and Glens"], "PH107JT": ["56.649693", "-3.344776", "S12000048", "Perth and Kinross", "S13003065", "Blairgowrie and Glens"], "PH107JU": ["56.676164", "-3.352264", "S12000048", "Perth and Kinross", "S13003064", "Strathmore"], "PH107JW": ["56.662831", "-3.397780", "S12000048", "Perth and Kinross", "S13003065", "Blairgowrie and Glens"], "PH107JX": ["56.692373", "-3.402385", "S12000048", "Perth and Kinross", "S13003065", "Blairgowrie and Glens"], "PH107JY": ["56.721273", "-3.390846", "S12000048", "Perth and Kinross", "S13003065", "Blairgowrie and Glens"], "PH107JZ": ["56.726239", "-3.389477", "S12000048", "Perth and Kinross", "S13003065", "Blairgowrie and Glens"], "PH107LA": ["56.732237", "-3.379074", "S12000048", "Perth and Kinross", "S13003065", "Blairgowrie and Glens"], "PH107LG": ["56.655255", "-3.405868", "S12000048", "Perth and Kinross", "S13003065", "Blairgowrie and Glens"], "PH107LH": ["56.699865", "-3.412986", "S12000048", "Perth and Kinross", "S13003065", "Blairgowrie and Glens"], "PH107LJ": ["56.712400", "-3.407346", "S12000048", "Perth and Kinross", "S13003065", "Blairgowrie and Glens"], "PH107LL": ["56.727636", "-3.392258", "S12000048", "Perth and Kinross", "S13003065", "Blairgowrie and Glens"], "PH107LN": ["56.737917", "-3.392850", "S12000048", "Perth and Kinross", "S13003065", "Blairgowrie and Glens"], "PH107LP": ["56.759035", "-3.397313", "S12000048", "Perth and Kinross", "S13003065", "Blairgowrie and Glens"], "PH107LQ": ["56.676703", "-3.410584", "S12000048", "Perth and Kinross", "S13003065", "Blairgowrie and Glens"], "PH107LR": ["56.730986", "-3.405212", "S12000048", "Perth and Kinross", "S13003065", "Blairgowrie and Glens"], "PH107LS": ["56.716693", "-3.428796", "S12000048", "Perth and Kinross", "S13003065", "Blairgowrie and Glens"], "PH107LT": ["56.721819", "-3.453960", "S12000048", "Perth and Kinross", "S13003065", "Blairgowrie and Glens"], "PH107LU": ["56.716582", "-3.480455", "S12000048", "Perth and Kinross", "S13003065", "Blairgowrie and Glens"], "PH107LW": ["56.748569", "-3.393065", "S12000048", "Perth and Kinross", "S13003065", "Blairgowrie and Glens"], "PH107LX": ["56.713277", "-3.508982", "S12000048", "Perth and Kinross", "S13003065", "Blairgowrie and Glens"], "PH107LY": ["56.722254", "-3.507365", "S12000048", "Perth and Kinross", "S13003065", "Blairgowrie and Glens"], "PH107LZ": ["56.722078", "-3.508550", "S12000048", "Perth and Kinross", "S13003065", "Blairgowrie and Glens"], "PH107NA": ["56.718709", "-3.521063", "S12000048", "Perth and Kinross", "S13003065", "Blairgowrie and Glens"], "PH107NB": ["56.723348", "-3.516446", "S12000048", "Perth and Kinross", "S13003065", "Blairgowrie and Glens"], "PH107ND": ["56.721751", "-3.506593", "S12000048", "Perth and Kinross", "S13003065", "Blairgowrie and Glens"], "PH107NG": ["56.664412", "-3.448827", "S12000048", "Perth and Kinross", "S13003065", "Blairgowrie and Glens"], "PH107NH": ["56.675146", "-3.462933", "S12000048", "Perth and Kinross", "S13003065", "Blairgowrie and Glens"], "PH107NJ": ["56.678409", "-3.468136", "S12000048", "Perth and Kinross", "S13003065", "Blairgowrie and Glens"], "PH107NL": ["56.684018", "-3.470215", "S12000048", "Perth and Kinross", "S13003065", "Blairgowrie and Glens"], "PH107NN": ["56.687602", "-3.473359", "S12000048", "Perth and Kinross", "S13003065", "Blairgowrie and Glens"], "PH107NP": ["56.712918", "-3.487255", "S12000048", "Perth and Kinross", "S13003065", "Blairgowrie and Glens"], "PH107NQ": ["56.668128", "-3.451466", "S12000048", "Perth and Kinross", "S13003065", "Blairgowrie and Glens"], "PH107NR": ["56.720139", "-3.495711", "S12000048", "Perth and Kinross", "S13003065", "Blairgowrie and Glens"], "PH107NS": ["56.721750", "-3.500710", "S12000048", "Perth and Kinross", "S13003065", "Blairgowrie and Glens"], "PH107NT": ["56.724104", "-3.505232", "S12000048", "Perth and Kinross", "S13003065", "Blairgowrie and Glens"], "PH107NU": ["56.724004", "-3.506078", "S12000048", "Perth and Kinross", "S13003065", "Blairgowrie and Glens"], "PH107NW": ["56.691529", "-3.485383", "S12000048", "Perth and Kinross", "S13003065", "Blairgowrie and Glens"], "PH107NX": ["56.722736", "-3.506142", "S12000048", "Perth and Kinross", "S13003065", "Blairgowrie and Glens"], "PH107NY": ["56.720918", "-3.504206", "S12000048", "Perth and Kinross", "S13003065", "Blairgowrie and Glens"], "PH107NZ": ["56.727768", "-3.509824", "S12000048", "Perth and Kinross", "S13003065", "Blairgowrie and Glens"], "PH107PA": ["56.734743", "-3.517509", "S12000048", "Perth and Kinross", "S13003065", "Blairgowrie and Glens"], "PH107PB": ["56.745942", "-3.526268", "S12000048", "Perth and Kinross", "S13003065", "Blairgowrie and Glens"], "PH107PD": ["56.753651", "-3.529901", "S12000048", "Perth and Kinross", "S13003065", "Blairgowrie and Glens"], "PH107PE": ["56.746624", "-3.534341", "S12000048", "Perth and Kinross", "S13003065", "Blairgowrie and Glens"], "PH107PF": ["56.745943", "-3.539333", "S12000048", "Perth and Kinross", "S13003065", "Blairgowrie and Glens"], "PH107PG": ["56.748477", "-3.547303", "S12000048", "Perth and Kinross", "S13003065", "Blairgowrie and Glens"], "PH107PH": ["56.759509", "-3.569660", "S12000048", "Perth and Kinross", "S13003065", "Blairgowrie and Glens"], "PH107PJ": ["56.755911", "-3.618432", "S12000048", "Perth and Kinross", "S13003065", "Blairgowrie and Glens"], "PH107PL": ["56.766700", "-3.561550", "S12000048", "Perth and Kinross", "S13003065", "Blairgowrie and Glens"], "PH107PN": ["56.900352", "-3.628190", "S12000048", "Perth and Kinross", "S13003065", "Blairgowrie and Glens"], "PH107PQ": ["56.753779", "-3.572365", "S12000048", "Perth and Kinross", "S13003065", "Blairgowrie and Glens"], "PH107PU": ["56.672682", "-3.472287", "S12000048", "Perth and Kinross", "S13003065", "Blairgowrie and Glens"], "PH107PW": ["56.751786", "-3.541796", "S12000048", "Perth and Kinross", "S13003065", "Blairgowrie and Glens"], "PH107PX": ["56.660239", "-3.457673", "S12000048", "Perth and Kinross", "S13003065", "Blairgowrie and Glens"], "PH107PY": ["56.683293", "-3.487360", "S12000048", "Perth and Kinross", "S13003065", "Blairgowrie and Glens"], "PH107PZ": ["56.694125", "-3.495250", "S12000048", "Perth and Kinross", "S13003065", "Blairgowrie and Glens"], "PH107QB": ["56.779935", "-3.408384", "S12000048", "Perth and Kinross", "S13003065", "Blairgowrie and Glens"], "PH107QD": ["56.798398", "-3.430462", "S12000048", "Perth and Kinross", "S13003065", "Blairgowrie and Glens"], "PH107QE": ["56.812203", "-3.469564", "S12000048", "Perth and Kinross", "S13003065", "Blairgowrie and Glens"], "PH107QF": ["56.812206", "-3.458573", "S12000048", "Perth and Kinross", "S13003065", "Blairgowrie and Glens"], "PH107QG": ["56.823652", "-3.490544", "S12000048", "Perth and Kinross", "S13003065", "Blairgowrie and Glens"], "PH107QH": ["56.594150", "-3.332362", "S12000048", "Perth and Kinross", "S13003065", "Blairgowrie and Glens"], "PH107QQ": ["56.850263", "-3.432326", "S12000048", "Perth and Kinross", "S13003065", "Blairgowrie and Glens"], "PH107RA": ["56.594829", "-3.324357", "S12000048", "Perth and Kinross", "S13003065", "Blairgowrie and Glens"], "PH107RB": ["56.594529", "-3.324607", "S12000048", "Perth and Kinross", "S13003065", "Blairgowrie and Glens"], "PH107RD": ["56.594189", "-3.325377", "S12000048", "Perth and Kinross", "S13003065", "Blairgowrie and Glens"], "PH107RE": ["56.595355", "-3.326395", "S12000048", "Perth and Kinross", "S13003065", "Blairgowrie and Glens"], "PH107WA": ["56.595288", "-3.326784", "S12000048", "Perth and Kinross", "S13003065", "Blairgowrie and Glens"], "PH107WU": ["56.588603", "-3.334333", "S12000048", "Perth and Kinross", "S13003065", "Blairgowrie and Glens"], "PH107WW": ["56.588603", "-3.334333", "S12000048", "Perth and Kinross", "S13003065", "Blairgowrie and Glens"], "PH107WX": ["56.588603", "-3.334333", "S12000048", "Perth and Kinross", "S13003065", "Blairgowrie and Glens"], "PH107YA": ["56.588603", "-3.334333", "S12000048", "Perth and Kinross", "S13003065", "Blairgowrie and Glens"], "PH107YB": ["56.634570", "-3.365774", "S12000048", "Perth and Kinross", "S13003065", "Blairgowrie and Glens"], "PH107YD": ["56.588488", "-3.334150", "S12000048", "Perth and Kinross", "S13003065", "Blairgowrie and Glens"], "PH107YE": ["56.588488", "-3.334150", "S12000048", "Perth and Kinross", "S13003065", "Blairgowrie and Glens"], "PH107YG": ["56.588488", "-3.334150", "S12000048", "Perth and Kinross", "S13003065", "Blairgowrie and Glens"], "PH107YH": ["56.588603", "-3.334333", "S12000048", "Perth and Kinross", "S13003065", "Blairgowrie and Glens"]}