{"SN66JJ": ["51.659802", "-1.792772", "E06000030", "Swindon", "E05010755", "Blunsdon and Highworth"], "SN66JX": ["51.658559", "-1.791057", "E06000030", "Swindon", "E05010755", "Blunsdon and Highworth"], "SN66JY": ["51.659893", "-1.793148", "E06000030", "Swindon", "E05010755", "Blunsdon and Highworth"], "SN66JZ": ["51.660684", "-1.791152", "E06000030", "Swindon", "E05010755", "Blunsdon and Highworth"], "SN66LA": ["51.660803", "-1.789153", "E06000030", "Swindon", "E05010755", "Blunsdon and Highworth"], "SN66LB": ["51.660821", "-1.789139", "E06000030", "Swindon", "E05010755", "Blunsdon and Highworth"], "SN66LD": ["51.660827", "-1.787751", "E06000030", "Swindon", "E05010755", "Blunsdon and Highworth"], "SN66LE": ["51.661153", "-1.783817", "E06000030", "Swindon", "E05010755", "Blunsdon and Highworth"], "SN66LF": ["51.659833", "-1.789895", "E06000030", "Swindon", "E05010755", "Blunsdon and Highworth"], "SN66LN": ["51.673774", "-1.832043", "E07000079", "Cotswold", "E05010724", "The Ampneys & Hampton"], "SN66WD": ["51.562676", "-1.818214", "E06000030", "Swindon", "E05008962", "Mannington and Western"], "SN66WR": ["51.562676", "-1.818214", "E06000030", "Swindon", "E05008962", "Mannington and Western"]}